{"source": "nottingham", "song_id": "reelsr-t46", "title": "Sir Sidney Smith", "artist": "", "style": "folk/reelsr-t", "key": "G", "mode": "", "transpose_offset": 5, "bpm": null, "beats_per_bar": 4, "n_bars": 65, "bars": [{"bar": 0, "beats_per_bar": 4, "notes": [[71, 3.0, 0.5, 100], [72, 3.5, 0.5, 100]], "chords": [], "next_chord": "G:maj", "next_chord_t": "C:maj"}, {"bar": 1, "beats_per_bar": 4, "notes": [[74, 0.0, 1.0, 100], [74, 1.0, 1.0, 100], [74, 2.0, 1.0, 100], [74, 3.0, 1.0, 100]], "chords": [{"label": "G:maj", "raw": "G", "t": "C:maj", "onset": 0.0}], "next_chord": "G:maj", "next_chord_t": "C:maj"}, {"bar": 2, "beats_per_bar": 4, "notes": [[76, 0.0, 1.0, 100], [74, 1.0, 1.0, 100], [72, 2.0, 1.0, 100], [71, 3.0, 1.0, 100]], "chords": [{"label": "G:maj", "raw": "G", "t": "C:maj", "onset": 0.0}], "next_chord": "C:maj", "next_chord_t": "F:maj"}, {"bar": 3, "beats_per_bar": 4, "notes": [[74, 0.0, 0.5, 100], [72, 0.5, 0.5, 100], [71, 1.0, 0.5, 100], [72, 1.5, 0.5, 100], [69, 2.0, 1.0, 100], [74, 3.0, 0.5, 100], [72, 3.5, 0.5, 100]], "chords": [{"label": "C:maj", "raw": "C", "t": "F:maj", "onset": 0.0}, {"label": "D:7", "raw": "D7", "t": "G:7", "onset": 2.0}], "next_chord": "G:maj", "next_chord_t": "C:maj"}, {"bar": 4, "beats_per_bar": 4, "notes": [[71, 0.0, 0.5, 100], [72, 0.5, 0.5, 100], [69, 1.0, 0.5, 100], [71, 1.5, 0.5, 100], [67, 2.0, 1.0, 100], [74, 3.0, 0.5, 100], [72, 3.5, 0.5, 100]], "chords": [{"label": "G:maj", "raw": "G", "t": "C:maj", "onset": 0.0}, {"label": "D:maj", "raw": "D", "t": "G:maj", "onset": 1.0}, {"label": "G:maj", "raw": "G", "t": "C:maj", "onset": 2.0}], "next_chord": "G:maj", "next_chord_t": "C:maj"}, {"bar": 5, "beats_per_bar": 4, "notes": [[71, 0.0, 0.5, 100], [74, 0.5, 0.5, 100], [71, 1.0, 0.5, 100], [74, 1.5, 0.5, 100], [69, 2.0, 0.5, 100], [74, 2.5, 0.5, 100], [69, 3.0, 0.5, 100], [74, 3.5, 0.5, 100]], "chords": [{"label": "G:maj", "raw": "G", "t": "C:maj", "onset": 0.0}, {"label": "D:maj", "raw": "D", "t": "G:maj", "onset": 2.0}], "next_chord": "E:min", "next_chord_t": "A:min"}, {"bar": 6, "beats_per_bar": 4, "notes": [[67, 0.0, 0.5, 100], [74, 0.5, 0.5, 100], [67, 1.0, 0.5, 100], [74, 1.5, 0.5, 100], [66, 2.0, 1.0, 100], [74, 3.0, 0.5, 100], [72, 3.5, 0.5, 100]], "chords": [{"label": "E:min", "raw": "Em", "t": "A:min", "onset": 0.0}, {"label": "B:min", "raw": "Bm", "t": "E:min", "onset": 2.0}], "next_chord": "E:min", "next_chord_t": "A:min"}, {"bar": 7, "beats_per_bar": 4, "notes": [[71, 0.0, 0.5, 100], [72, 0.5, 0.5, 100], [74, 1.0, 0.5, 100], [76, 1.5, 0.5, 100], [74, 2.0, 1.0, 100], [73, 3.0, 1.0, 100]], "chords": [{"label": "E:min", "raw": "Em", "t": "A:min", "onset": 0.0}, {"label": "A:7", "raw": "A7", "t": "D:7", "onset": 2.0}], "next_chord": "D:maj", "next_chord_t": "G:maj"}, {"bar": 8, "beats_per_bar": 4, "notes": [[74, 0.0, 3.0, 100], [71, 3.0, 0.5, 100], [72, 3.5, 0.5, 100]], "chords": [{"label": "D:maj", "raw": "D", "t": "G:maj", "onset": 0.0}], "next_chord": "G:maj", "next_chord_t": "C:maj"}, {"bar": 9, "beats_per_bar": 4, "notes": [[74, 0.0, 1.0, 100], [74, 1.0, 1.0, 100], [74, 2.0, 1.0, 100], [74, 3.0, 1.0, 100]], "chords": [{"label": "G:maj", "raw": "G", "t": "C:maj", "onset": 0.0}], "next_chord": "G:maj", "next_chord_t": "C:maj"}, {"bar": 10, "beats_per_bar": 4, "notes": [[76, 0.0, 1.0, 100], [74, 1.0, 1.0, 100], [72, 2.0, 1.0, 100], [71, 3.0, 1.0, 100]], "chords": [{"label": "G:maj", "raw": "G", "t": "C:maj", "onset": 0.0}], "next_chord": "C:maj", "next_chord_t": "F:maj"}, {"bar": 11, "beats_per_bar": 4, "notes": [[74, 0.0, 0.5, 100], [72, 0.5, 0.5, 100], [71, 1.0, 0.5, 100], [72, 1.5, 0.5, 100], [69, 2.0, 1.0, 100], [74, 3.0, 0.5, 100], [72, 3.5, 0.5, 100]], "chords": [{"label": "C:maj", "raw": "C", "t": "F:maj", "onset": 0.0}, {"label": "D:7", "raw": "D7", "t": "G:7", "onset": 2.0}], "next_chord": "G:maj", "next_chord_t": "C:maj"}, {"bar": 12, "beats_per_bar": 4, "notes": [[71, 0.0, 0.5, 100], [72, 0.5, 0.5, 100], [69, 1.0, 0.5, 100], [71, 1.5, 0.5, 100], [67, 2.0, 1.0, 100], [74, 3.0, 0.5, 100], [72, 3.5, 0.5, 100]], "chords": [{"label": "G:maj", "raw": "G", "t": "C:maj", "onset": 0.0}, {"label": "D:maj", "raw": "D", "t": "G:maj", "onset": 1.0}, {"label": "G:maj", "raw": "G", "t": "C:maj", "onset": 2.0}], "next_chord": "G:maj", "next_chord_t": "C:maj"}, {"bar": 13, "beats_per_bar": 4, "notes": [[71, 0.0, 0.5, 100], [74, 0.5, 0.5, 100], [71, 1.0, 0.5, 100], [74, 1.5, 0.5, 100], [69, 2.0, 0.5, 100], [74, 2.5, 0.5, 100], [69, 3.0, 0.5, 100], [74, 3.5, 0.5, 100]], "chords": [{"label": "G:maj", "raw": "G", "t": "C:maj", "onset": 0.0}, {"label": "D:maj", "raw": "D", "t": "G:maj", "onset": 2.0}], "next_chord": "E:min", "next_chord_t": "A:min"}, {"bar": 14, "beats_per_bar": 4, "notes": [[67, 0.0, 0.5, 100], [74, 0.5, 0.5, 100], [67, 1.0, 0.5, 100], [74, 1.5, 0.5, 100], [66, 2.0, 1.0, 100], [74, 3.0, 0.5, 100], [72, 3.5, 0.5, 100]], "chords": [{"label": "E:min", "raw": "Em", "t": "A:min", "onset": 0.0}, {"label": "B:min", "raw": "Bm", "t": "E:min", "onset": 2.0}], "next_chord": "E:min", "next_chord_t": "A:min"}, {"bar": 15, "beats_per_bar": 4, "notes": [[71, 0.0, 0.5, 100], [72, 0.5, 0.5, 100], [74, 1.0, 0.5, 100], [76, 1.5, 0.5, 100], [74, 2.0, 1.0, 100], [73, 3.0, 1.0, 100]], "chords": [{"label": "E:min", "raw": "Em", "t": "A:min", "onset": 0.0}, {"label": "A:7", "raw": "A7", "t": "D:7", "onset": 2.0}], "next_chord": "D:maj", "next_chord_t": "G:maj"}, {"bar": 16, "beats_per_bar": 4, "notes": [[74, 0.0, 3.0, 100], [69, 3.0, 0.5, 100], [67, 3.5, 0.5, 100]], "chords": [{"label": "D:maj", "raw": "D", "t": "G:maj", "onset": 0.0}], "next_chord": "D:maj", "next_chord_t": "G:maj"}, {"bar": 17, "beats_per_bar": 4, "notes": [[66, 0.0, 0.5, 100], [62, 0.5, 0.5, 100], [66, 1.0, 0.5, 100], [69, 1.5, 0.5, 100], [74, 2.0, 0.5, 100], [69, 2.5, 0.5, 100], [71, 3.0, 0.5, 100], [72, 3.5, 0.5, 100]], "chords": [{"label": "D:maj", "raw": "D", "t": "G:maj", "onset": 0.0}], "next_chord": "G:maj", "next_chord_t": "C:maj"}, {"bar": 18, "beats_per_bar": 4, "notes": [[71, 0.0, 3.0, 100], [74, 3.0, 0.5, 100], [72, 3.5, 0.5, 100]], "chords": [{"label": "G:maj", "raw": "G", "t": "C:maj", "onset": 0.0}], "next_chord": "G:7", "next_chord_t": "C:7"}, {"bar": 19, "beats_per_bar": 4, "notes": [[71, 0.0, 0.5, 100], [67, 0.5, 0.5, 100], [71, 1.0, 0.5, 100], [74, 1.5, 0.5, 100], [79, 2.0, 0.5, 100], [74, 2.5, 0.5, 100], [76, 3.0, 0.5, 100], [77, 3.5, 0.5, 100]], "chords": [{"label": "G:7", "raw": "G7", "t": "C:7", "onset": 0.0}], "next_chord": "C:maj", "next_chord_t": "F:maj"}, {"bar": 20, "beats_per_bar": 4, "notes": [[76, 0.0, 3.0, 100], [79, 3.0, 0.5, 100], [78, 3.5, 0.5, 100]], "chords": [{"label": "C:maj", "raw": "C", "t": "F:maj", "onset": 0.0}], "next_chord": "C:maj", "next_chord_t": "F:maj"}, {"bar": 21, "beats_per_bar": 4, "notes": [[76, 0.0, 0.5, 100], [79, 0.5, 0.5, 100], [76, 1.0, 0.5, 100], [79, 1.5, 0.5, 100], [74, 2.0, 0.5, 100], [79, 2.5, 0.5, 100], [74, 3.0, 0.5, 100], [79, 3.5, 0.5, 100]], "chords": [{"label": "C:maj", "raw": "C", "t": "F:maj", "onset": 0.0}, {"label": "G:maj", "raw": "G", "t": "C:maj", "onset": 2.0}], "next_chord": "D:maj", "next_chord_t": "G:maj"}, {"bar": 22, "beats_per_bar": 4, "notes": [[72, 0.0, 0.5, 100], [79, 0.5, 0.5, 100], [72, 1.0, 0.5, 100], [79, 1.5, 0.5, 100], [71, 2.0, 0.5, 100], [79, 2.5, 0.5, 100], [71, 3.0, 0.5, 100], [79, 3.5, 0.5, 100]], "chords": [{"label": "D:maj", "raw": "D", "t": "G:maj", "onset": 0.0}, {"label": "G:maj", "raw": "G", "t": "C:maj", "onset": 2.0}], "next_chord": "C:maj", "next_chord_t": "F:maj"}, {"bar": 23, "beats_per_bar": 4, "notes": [[76, 0.0, 0.5, 100], [79, 0.5, 0.5, 100], [76, 1.0, 0.5, 100], [79, 1.5, 0.5, 100], [74, 2.0, 0.5, 100], [79, 2.5, 0.5, 100], [74, 3.0, 0.5, 100], [79, 3.5, 0.5, 100]], "chords": [{"label": "C:maj", "raw": "C", "t": "F:maj", "onset": 0.0}, {"label": "G:maj", "raw": "G", "t": "C:maj", "onset": 2.0}], "next_chord": "D:maj", "next_chord_t": "G:maj"}, {"bar": 24, "beats_per_bar": 4, "notes": [[72, 0.0, 0.5, 100], [79, 0.5, 0.5, 100], [72, 1.0, 0.5, 100], [79, 1.5, 0.5, 100], [71, 2.0, 0.5, 100], [79, 2.5, 0.5, 100], [71, 3.0, 0.5, 100], [79, 3.5, 0.5, 100]], "chords": [{"label": "D:maj", "raw": "D", "t": "G:maj", "onset": 0.0}, {"label": "G:maj", "raw": "G", "t": "C:maj", "onset": 2.0}], "next_chord": "G:maj", "next_chord_t": "C:maj"}, {"bar": 25, "beats_per_bar": 4, "notes": [[76, 0.0, 1.0, 100], [74, 1.0, 1.0, 100], [72, 2.0, 1.0, 100], [71, 3.0, 1.0, 100]], "chords": [{"label": "G:maj", "raw": "G", "t": "C:maj", "onset": 0.0}], "next_chord": "G:maj", "next_chord_t": "C:maj"}, {"bar": 26, "beats_per_bar": 4, "notes": [[76, 0.0, 1.0, 100], [74, 1.0, 1.0, 100], [72, 2.0, 1.0, 100], [71, 3.0, 1.0, 100]], "chords": [{"label": "G:maj", "raw": "G", "t": "C:maj", "onset": 0.0}], "next_chord": "G:maj", "next_chord_t": "C:maj"}, {"bar": 27, "beats_per_bar": 4, "notes": [[76, 0.0, 1.0, 100], [74, 1.0, 1.0, 100], [72, 2.0, 1.0, 100], [71, 3.0, 1.0, 100]], "chords": [{"label": "G:maj", "raw": "G", "t": "C:maj", "onset": 0.0}], "next_chord": "C:maj", "next_chord_t": "F:maj"}, {"bar": 28, "beats_per_bar": 4, "notes": [[71, 0.0, 1.0, 100], [69, 1.0, 1.0, 100], [69, 2.0, 1.0, 100], [71, 3.0, 0.5, 100], [72, 3.5, 0.5, 100]], "chords": [{"label": "C:maj", "raw": "C", "t": "F:maj", "onset": 0.0}, {"label": "A:7", "raw": "A7", "t": "D:7", "onset": 1.0}, {"label": "D:7", "raw": "D7", "t": "G:7", "onset": 2.0}], "next_chord": "G:maj", "next_chord_t": "C:maj"}, {"bar": 29, "beats_per_bar": 4, "notes": [[74, 0.0, 1.0, 100], [74, 1.0, 2.0, 100], [74, 3.0, 1.0, 100]], "chords": [{"label": "G:maj", "raw": "G", "t": "C:maj", "onset": 0.0}], "next_chord": "G:maj", "next_chord_t": "C:maj"}, {"bar": 30, "beats_per_bar": 4, "notes": [[76, 0.0, 1.0, 100], [74, 1.0, 1.0, 100], [72, 2.0, 1.0, 100], [71, 3.0, 1.0, 100]], "chords": [{"label": "G:maj", "raw": "G", "t": "C:maj", "onset": 0.0}], "next_chord": "C:maj", "next_chord_t": "F:maj"}, {"bar": 31, "beats_per_bar": 4, "notes": [[74, 0.0, 0.5, 100], [72, 0.5, 0.5, 100], [71, 1.0, 0.5, 100], [72, 1.5, 0.5, 100], [69, 2.0, 1.0, 100], [74, 3.0, 0.5, 100], [72, 3.5, 0.5, 100]], "chords": [{"label": "C:maj", "raw": "C", "t": "F:maj", "onset": 0.0}, {"label": "D:7", "raw": "D7", "t": "G:7", "onset": 2.0}], "next_chord": "G:maj", "next_chord_t": "C:maj"}, {"bar": 32, "beats_per_bar": 4, "notes": [[71, 0.0, 0.5, 100], [72, 0.5, 0.5, 100], [69, 1.0, 0.5, 100], [71, 1.5, 0.5, 100], [67, 2.0, 1.0, 100], [74, 3.0, 0.5, 100], [72, 3.5, 0.5, 100]], "chords": [{"label": "G:maj", "raw": "G", "t": "C:maj", "onset": 0.0}, {"label": "D:maj", "raw": "D", "t": "G:maj", "onset": 1.0}, {"label": "G:maj", "raw": "G", "t": "C:maj", "onset": 2.0}], "next_chord": "G:maj", "next_chord_t": "C:maj"}, {"bar": 33, "beats_per_bar": 4, "notes": [[71, 0.0, 0.5, 100], [74, 0.5, 0.5, 100], [71, 1.0, 0.5, 100], [74, 1.5, 0.5, 100], [69, 2.0, 0.5, 100], [74, 2.5, 0.5, 100], [69, 3.0, 0.5, 100], [74, 3.5, 0.5, 100]], "chords": [{"label": "G:maj", "raw": "G", "t": "C:maj", "onset": 0.0}, {"label": "D:maj", "raw": "D", "t": "G:maj", "onset": 2.0}], "next_chord": "E:min", "next_chord_t": "A:min"}, {"bar": 34, "beats_per_bar": 4, "notes": [[67, 0.0, 0.5, 100], [74, 0.5, 0.5, 100], [67, 1.0, 0.5, 100], [74, 1.5, 0.5, 100], [66, 2.0, 0.5, 100], [74, 2.5, 0.5, 100], [66, 3.0, 0.5, 100], [74, 3.5, 0.5, 100]], "chords": [{"label": "E:min", "raw": "Em", "t": "A:min", "onset": 0.0}, {"label": "D:maj", "raw": "D", "t": "G:maj", "onset": 2.0}], "next_chord": "C:maj", "next_chord_t": "F:maj"}, {"bar": 35, "beats_per_bar": 4, "notes": [[64, 0.0, 0.5, 100], [74, 0.5, 0.5, 100], [64, 1.0, 0.5, 100], [74, 1.5, 0.5, 100], [66, 2.0, 0.5, 100], [74, 2.5, 0.5, 100], [66, 3.0, 0.5, 100], [74, 3.5, 0.5, 100]], "chords": [{"label": "C:maj", "raw": "C", "t": "F:maj", "onset": 0.0}, {"label": "D:maj", "raw": "D", "t": "G:maj", "onset": 2.0}], "next_chord": "E:min", "next_chord_t": "A:min"}, {"bar": 36, "beats_per_bar": 4, "notes": [[67, 0.0, 0.5, 100], [74, 0.5, 0.5, 100], [67, 1.0, 0.5, 100], [74, 1.5, 0.5, 100], [69, 2.0, 0.5, 100], [74, 2.5, 0.5, 100], [69, 3.0, 0.5, 100], [74, 3.5, 0.5, 100]], "chords": [{"label": "E:min", "raw": "Em", "t": "A:min", "onset": 0.0}, {"label": "D:maj", "raw": "D", "t": "G:maj", "onset": 2.0}], "next_chord": "C:maj", "next_chord_t": "F:maj"}, {"bar": 37, "beats_per_bar": 4, "notes": [[64, 0.0, 0.5, 100], [74, 0.5, 0.5, 100], [64, 1.0, 0.5, 100], [74, 1.5, 0.5, 100], [66, 2.0, 0.5, 100], [74, 2.5, 0.5, 100], [66, 3.0, 0.5, 100], [74, 3.5, 0.5, 100]], "chords": [{"label": "C:maj", "raw": "C", "t": "F:maj", "onset": 0.0}, {"label": "D:maj", "raw": "D", "t": "G:maj", "onset": 2.0}], "next_chord": "E:min", "next_chord_t": "A:min"}, {"bar": 38, "beats_per_bar": 4, "notes": [[67, 0.0, 0.5, 100], [74, 0.5, 0.5, 100], [67, 1.0, 0.5, 100], [74, 1.5, 0.5, 100], [69, 2.0, 0.5, 100], [74, 2.5, 0.5, 100], [69, 3.0, 0.5, 100], [74, 3.5, 0.5, 100]], "chords": [{"label": "E:min", "raw": "Em", "t": "A:min", "onset": 0.0}, {"label": "D:maj", "raw": "D", "t": "G:maj", "onset": 2.0}], "next_chord": "C:maj", "next_chord_t": "F:maj"}, {"bar": 39, "beats_per_bar": 4, "notes": [[72, 0.0, 0.5, 100], [76, 0.5, 0.5, 100], [74, 1.0, 0.5, 100], [72, 1.5, 0.5, 100], [71, 2.0, 0.5, 100], [67, 2.5, 0.5, 100], [69, 3.0, 0.5, 100], [66, 3.5, 0.5, 100]], "chords": [{"label": "C:maj", "raw": "C", "t": "F:maj", "onset": 0.0}, {"label": "D:7", "raw": "D7", "t": "G:7", "onset": 2.0}], "next_chord": "G:maj", "next_chord_t": "C:maj"}, {"bar": 40, "beats_per_bar": 4, "notes": [[67, 0.0, 3.0, 100], [69, 3.0, 0.5, 100], [67, 3.5, 0.5, 100]], "chords": [{"label": "G:maj", "raw": "G", "t": "C:maj", "onset": 0.0}], "next_chord": "D:maj", "next_chord_t": "G:maj"}, {"bar": 41, "beats_per_bar": 4, "notes": [[66, 0.0, 0.5, 100], [62, 0.5, 0.5, 100], [66, 1.0, 0.5, 100], [69, 1.5, 0.5, 100], [74, 2.0, 0.5, 100], [69, 2.5, 0.5, 100], [71, 3.0, 0.5, 100], [72, 3.5, 0.5, 100]], "chords": [{"label": "D:maj", "raw": "D", "t": "G:maj", "onset": 0.0}], "next_chord": "G:maj", "next_chord_t": "C:maj"}, {"bar": 42, "beats_per_bar": 4, "notes": [[71, 0.0, 3.0, 100], [74, 3.0, 0.5, 100], [72, 3.5, 0.5, 100]], "chords": [{"label": "G:maj", "raw": "G", "t": "C:maj", "onset": 0.0}], "next_chord": "G:7", "next_chord_t": "C:7"}, {"bar": 43, "beats_per_bar": 4, "notes": [[71, 0.0, 0.5, 100], [67, 0.5, 0.5, 100], [71, 1.0, 0.5, 100], [74, 1.5, 0.5, 100], [79, 2.0, 0.5, 100], [74, 2.5, 0.5, 100], [76, 3.0, 0.5, 100], [77, 3.5, 0.5, 100]], "chords": [{"label": "G:7", "raw": "G7", "t": "C:7", "onset": 0.0}], "next_chord": "C:maj", "next_chord_t": "F:maj"}, {"bar": 44, "beats_per_bar": 4, "notes": [[76, 0.0, 3.0, 100], [79, 3.0, 0.5, 100], [78, 3.5, 0.5, 100]], "chords": [{"label": "C:maj", "raw": "C", "t": "F:maj", "onset": 0.0}], "next_chord": "C:maj", "next_chord_t": "F:maj"}, {"bar": 45, "beats_per_bar": 4, "notes": [[76, 0.0, 0.5, 100], [79, 0.5, 0.5, 100], [76, 1.0, 0.5, 100], [79, 1.5, 0.5, 100], [74, 2.0, 0.5, 100], [79, 2.5, 0.5, 100], [74, 3.0, 0.5, 100], [79, 3.5, 0.5, 100]], "chords": [{"label": "C:maj", "raw": "C", "t": "F:maj", "onset": 0.0}, {"label": "G:maj", "raw": "G", "t": "C:maj", "onset": 2.0}], "next_chord": "D:maj", "next_chord_t": "G:maj"}, {"bar": 46, "beats_per_bar": 4, "notes": [[72, 0.0, 0.5, 100], [79, 0.5, 0.5, 100], [72, 1.0, 0.5, 100], [79, 1.5, 0.5, 100], [71, 2.0, 0.5, 100], [79, 2.5, 0.5, 100], [71, 3.0, 0.5, 100], [79, 3.5, 0.5, 100]], "chords": [{"label": "D:maj", "raw": "D", "t": "G:maj", "onset": 0.0}, {"label": "G:maj", "raw": "G", "t": "C:maj", "onset": 2.0}], "next_chord": "C:maj", "next_chord_t": "F:maj"}, {"bar": 47, "beats_per_bar": 4, "notes": [[76, 0.0, 0.5, 100], [79, 0.5, 0.5, 100], [76, 1.0, 0.5, 100], [79, 1.5, 0.5, 100], [74, 2.0, 0.5, 100], [79, 2.5, 0.5, 100], [74, 3.0, 0.5, 100], [79, 3.5, 0.5, 100]], "chords": [{"label": "C:maj", "raw": "C", "t": "F:maj", "onset": 0.0}, {"label": "G:maj", "raw": "G", "t": "C:maj", "onset": 2.0}], "next_chord": "D:maj", "next_chord_t": "G:maj"}, {"bar": 48, "beats_per_bar": 4, "notes": [[72, 0.0, 0.5, 100], [79, 0.5, 0.5, 100], [72, 1.0, 0.5, 100], [79, 1.5, 0.5, 100], [71, 2.0, 0.5, 100], [79, 2.5, 0.5, 100], [71, 3.0, 0.5, 100], [79, 3.5, 0.5, 100]], "chords": [{"label": "D:maj", "raw": "D", "t": "G:maj", "onset": 0.0}, {"label": "G:maj", "raw": "G", "t": "C:maj", "onset": 2.0}], "next_chord": "G:maj", "next_chord_t": "C:maj"}, {"bar": 49, "beats_per_bar": 4, "notes": [[76, 0.0, 1.0, 100], [74, 1.0, 1.0, 100], [72, 2.0, 1.0, 100], [71, 3.0, 1.0, 100]], "chords": [{"label": "G:maj", "raw": "G", "t": "C:maj", "onset": 0.0}], "next_chord": "G:maj", "next_chord_t": "C:maj"}, {"bar": 50, "beats_per_bar": 4, "notes": [[76, 0.0, 1.0, 100], [74, 1.0, 1.0, 100], [72, 2.0, 1.0, 100], [71, 3.0, 1.0, 100]], "chords": [{"label": "G:maj", "raw": "G", "t": "C:maj", "onset": 0.0}], "next_chord": "G:maj", "next_chord_t": "C:maj"}, {"bar": 51, "beats_per_bar": 4, "notes": [[76, 0.0, 1.0, 100], [74, 1.0, 1.0, 100], [72, 2.0, 1.0, 100], [71, 3.0, 1.0, 100]], "chords": [{"label": "G:maj", "raw": "G", "t": "C:maj", "onset": 0.0}], "next_chord": "C:maj", "next_chord_t": "F:maj"}, {"bar": 52, "beats_per_bar": 4, "notes": [[71, 0.0, 1.0, 100], [69, 1.0, 1.0, 100], [69, 2.0, 1.0, 100], [71, 3.0, 0.5, 100], [72, 3.5, 0.5, 100]], "chords": [{"label": "C:maj", "raw": "C", "t": "F:maj", "onset": 0.0}, {"label": "A:7", "raw": "A7", "t": "D:7", "onset": 1.0}, {"label": "D:7", "raw": "D7", "t": "G:7", "onset": 2.0}], "next_chord": "G:maj", "next_chord_t": "C:maj"}, {"bar": 53, "beats_per_bar": 4, "notes": [[74, 0.0, 1.0, 100], [74, 1.0, 2.0, 100], [74, 3.0, 1.0, 100]], "chords": [{"label": "G:maj", "raw": "G", "t": "C:maj", "onset": 0.0}], "next_chord": "G:maj", "next_chord_t": "C:maj"}, {"bar": 54, "beats_per_bar": 4, "notes": [[76, 0.0, 1.0, 100], [74, 1.0, 1.0, 100], [72, 2.0, 1.0, 100], [71, 3.0, 1.0, 100]], "chords": [{"label": "G:maj", "raw": "G", "t": "C:maj", "onset": 0.0}], "next_chord": "C:maj", "next_chord_t": "F:maj"}, {"bar": 55, "beats_per_bar": 4, "notes": [[74, 0.0, 0.5, 100], [72, 0.5, 0.5, 100], [71, 1.0, 0.5, 100], [72, 1.5, 0.5, 100], [69, 2.0, 1.0, 100], [74, 3.0, 0.5, 100], [72, 3.5, 0.5, 100]], "chords": [{"label": "C:maj", "raw": "C", "t": "F:maj", "onset": 0.0}, {"label": "D:7", "raw": "D7", "t": "G:7", "onset": 2.0}], "next_chord": "G:maj", "next_chord_t": "C:maj"}, {"bar": 56, "beats_per_bar": 4, "notes": [[71, 0.0, 0.5, 100], [72, 0.5, 0.5, 100], [69, 1.0, 0.5, 100], [71, 1.5, 0.5, 100], [67, 2.0, 1.0, 100], [74, 3.0, 0.5, 100], [72, 3.5, 0.5, 100]], "chords": [{"label": "G:maj", "raw": "G", "t": "C:maj", "onset": 0.0}, {"label": "D:maj", "raw": "D", "t": "G:maj", "onset": 1.0}, {"label": "G:maj", "raw": "G", "t": "C:maj", "onset": 2.0}], "next_chord": "G:maj", "next_chord_t": "C:maj"}, {"bar": 57, "beats_per_bar": 4, "notes": [[71, 0.0, 0.5, 100], [74, 0.5, 0.5, 100], [71, 1.0, 0.5, 100], [74, 1.5, 0.5, 100], [69, 2.0, 0.5, 100], [74, 2.5, 0.5, 100], [69, 3.0, 0.5, 100], [74, 3.5, 0.5, 100]], "chords": [{"label": "G:maj", "raw": "G", "t": "C:maj", "onset": 0.0}, {"label": "D:maj", "raw": "D", "t": "G:maj", "onset": 2.0}], "next_chord": "E:min", "next_chord_t": "A:min"}, {"bar": 58, "beats_per_bar": 4, "notes": [[67, 0.0, 0.5, 100], [74, 0.5, 0.5, 100], [67, 1.0, 0.5, 100], [74, 1.5, 0.5, 100], [66, 2.0, 0.5, 100], [74, 2.5, 0.5, 100], [66, 3.0, 0.5, 100], [74, 3.5, 0.5, 100]], "chords": [{"label": "E:min", "raw": "Em", "t": "A:min", "onset": 0.0}, {"label": "D:maj", "raw": "D", "t": "G:maj", "onset": 2.0}], "next_chord": "C:maj", "next_chord_t": "F:maj"}, {"bar": 59, "beats_per_bar": 4, "notes": [[64, 0.0, 0.5, 100], [74, 0.5, 0.5, 100], [64, 1.0, 0.5, 100], [74, 1.5, 0.5, 100], [66, 2.0, 0.5, 100], [74, 2.5, 0.5, 100], [66, 3.0, 0.5, 100], [74, 3.5, 0.5, 100]], "chords": [{"label": "C:maj", "raw": "C", "t": "F:maj", "onset": 0.0}, {"label": "D:maj", "raw": "D", "t": "G:maj", "onset": 2.0}], "next_chord": "E:min", "next_chord_t": "A:min"}, {"bar": 60, "beats_per_bar": 4, "notes": [[67, 0.0, 0.5, 100], [74, 0.5, 0.5, 100], [67, 1.0, 0.5, 100], [74, 1.5, 0.5, 100], [69, 2.0, 0.5, 100], [74, 2.5, 0.5, 100], [69, 3.0, 0.5, 100], [74, 3.5, 0.5, 100]], "chords": [{"label": "E:min", "raw": "Em", "t": "A:min", "onset": 0.0}, {"label": "D:maj", "raw": "D", "t": "G:maj", "onset": 2.0}], "next_chord": "C:maj", "next_chord_t": "F:maj"}, {"bar": 61, "beats_per_bar": 4, "notes": [[64, 0.0, 0.5, 100], [74, 0.5, 0.5, 100], [64, 1.0, 0.5, 100], [74, 1.5, 0.5, 100], [66, 2.0, 0.5, 100], [74, 2.5, 0.5, 100], [66, 3.0, 0.5, 100], [74, 3.5, 0.5, 100]], "chords": [{"label": "C:maj", "raw": "C", "t": "F:maj", "onset": 0.0}, {"label": "D:maj", "raw": "D", "t": "G:maj", "onset": 2.0}], "next_chord": "E:min", "next_chord_t": "A:min"}, {"bar": 62, "beats_per_bar": 4, "notes": [[67, 0.0, 0.5, 100], [74, 0.5, 0.5, 100], [67, 1.0, 0.5, 100], [74, 1.5, 0.5, 100], [69, 2.0, 0.5, 100], [74, 2.5, 0.5, 100], [69, 3.0, 0.5, 100], [74, 3.5, 0.5, 100]], "chords": [{"label": "E:min", "raw": "Em", "t": "A:min", "onset": 0.0}, {"label": "D:maj", "raw": "D", "t": "G:maj", "onset": 2.0}], "next_chord": "C:maj", "next_chord_t": "F:maj"}, {"bar": 63, "beats_per_bar": 4, "notes": [[72, 0.0, 0.5, 100], [76, 0.5, 0.5, 100], [74, 1.0, 0.5, 100], [72, 1.5, 0.5, 100], [71, 2.0, 0.5, 100], [67, 2.5, 0.5, 100], [69, 3.0, 0.5, 100], [66, 3.5, 0.5, 100]], "chords": [{"label": "C:maj", "raw": "C", "t": "F:maj", "onset": 0.0}, {"label": "D:7", "raw": "D7", "t": "G:7", "onset": 2.0}], "next_chord": "G:maj", "next_chord_t": "C:maj"}, {"bar": 64, "beats_per_bar": 4, "notes": [[67, 0.0, 3.0, 100]], "chords": [{"label": "G:maj", "raw": "G", "t": "C:maj", "onset": 0.0}], "next_chord": null, "next_chord_t": null}], "chord_sequence": [{"chord": "G:maj", "raw": "G", "t": "C:maj", "bar": 1, "beat": 0.0, "dur": 8.0}, {"chord": "C:maj", "raw": "C", "t": "F:maj", "bar": 3, "beat": 0.0, "dur": 2.0}, {"chord": "D:7", "raw": "D7", "t": "G:7", "bar": 3, "beat": 2.0, "dur": 2.0}, {"chord": "G:maj", "raw": "G", "t": "C:maj", "bar": 4, "beat": 0.0, "dur": 1.0}, {"chord": "D:maj", "raw": "D", "t": "G:maj", "bar": 4, "beat": 1.0, "dur": 1.0}, {"chord": "G:maj", "raw": "G", "t": "C:maj", "bar": 4, "beat": 2.0, "dur": 4.0}, {"chord": "D:maj", "raw": "D", "t": "G:maj", "bar": 5, "beat": 2.0, "dur": 2.0}, {"chord": "E:min", "raw": "Em", "t": "A:min", "bar": 6, "beat": 0.0, "dur": 2.0}, {"chord": "B:min", "raw": "Bm", "t": "E:min", "bar": 6, "beat": 2.0, "dur": 2.0}, {"chord": "E:min", "raw": "Em", "t": "A:min", "bar": 7, "beat": 0.0, "dur": 2.0}, {"chord": "A:7", "raw": "A7", "t": "D:7", "bar": 7, "beat": 2.0, "dur": 2.0}, {"chord": "D:maj", "raw": "D", "t": "G:maj", "bar": 8, "beat": 0.0, "dur": 4.0}, {"chord": "G:maj", "raw": "G", "t": "C:maj", "bar": 9, "beat": 0.0, "dur": 8.0}, {"chord": "C:maj", "raw": "C", "t": "F:maj", "bar": 11, "beat": 0.0, "dur": 2.0}, {"chord": "D:7", "raw": "D7", "t": "G:7", "bar": 11, "beat": 2.0, "dur": 2.0}, {"chord": "G:maj", "raw": "G", "t": "C:maj", "bar": 12, "beat": 0.0, "dur": 1.0}, {"chord": "D:maj", "raw": "D", "t": "G:maj", "bar": 12, "beat": 1.0, "dur": 1.0}, {"chord": "G:maj", "raw": "G", "t": "C:maj", "bar": 12, "beat": 2.0, "dur": 4.0}, {"chord": "D:maj", "raw": "D", "t": "G:maj", "bar": 13, "beat": 2.0, "dur": 2.0}, {"chord": "E:min", "raw": "Em", "t": "A:min", "bar": 14, "beat": 0.0, "dur": 2.0}, {"chord": "B:min", "raw": "Bm", "t": "E:min", "bar": 14, "beat": 2.0, "dur": 2.0}, {"chord": "E:min", "raw": "Em", "t": "A:min", "bar": 15, "beat": 0.0, "dur": 2.0}, {"chord": "A:7", "raw": "A7", "t": "D:7", "bar": 15, "beat": 2.0, "dur": 2.0}, {"chord": "D:maj", "raw": "D", "t": "G:maj", "bar": 16, "beat": 0.0, "dur": 8.0}, {"chord": "G:maj", "raw": "G", "t": "C:maj", "bar": 18, "beat": 0.0, "dur": 4.0}, {"chord": "G:7", "raw": "G7", "t": "C:7", "bar": 19, "beat": 0.0, "dur": 4.0}, {"chord": "C:maj", "raw": "C", "t": "F:maj", "bar": 20, "beat": 0.0, "dur": 6.0}, {"chord": "G:maj", "raw": "G", "t": "C:maj", "bar": 21, "beat": 2.0, "dur": 2.0}, {"chord": "D:maj", "raw": "D", "t": "G:maj", "bar": 22, "beat": 0.0, "dur": 2.0}, {"chord": "G:maj", "raw": "G", "t": "C:maj", "bar": 22, "beat": 2.0, "dur": 2.0}, {"chord": "C:maj", "raw": "C", "t": "F:maj", "bar": 23, "beat": 0.0, "dur": 2.0}, {"chord": "G:maj", "raw": "G", "t": "C:maj", "bar": 23, "beat": 2.0, "dur": 2.0}, {"chord": "D:maj", "raw": "D", "t": "G:maj", "bar": 24, "beat": 0.0, "dur": 2.0}, {"chord": "G:maj", "raw": "G", "t": "C:maj", "bar": 24, "beat": 2.0, "dur": 14.0}, {"chord": "C:maj", "raw": "C", "t": "F:maj", "bar": 28, "beat": 0.0, "dur": 1.0}, {"chord": "A:7", "raw": "A7", "t": "D:7", "bar": 28, "beat": 1.0, "dur": 1.0}, {"chord": "D:7", "raw": "D7", "t": "G:7", "bar": 28, "beat": 2.0, "dur": 2.0}, {"chord": "G:maj", "raw": "G", "t": "C:maj", "bar": 29, "beat": 0.0, "dur": 8.0}, {"chord": "C:maj", "raw": "C", "t": "F:maj", "bar": 31, "beat": 0.0, "dur": 2.0}, {"chord": "D:7", "raw": "D7", "t": "G:7", "bar": 31, "beat": 2.0, "dur": 2.0}, {"chord": "G:maj", "raw": "G", "t": "C:maj", "bar": 32, "beat": 0.0, "dur": 1.0}, {"chord": "D:maj", "raw": "D", "t": "G:maj", "bar": 32, "beat": 1.0, "dur": 1.0}, {"chord": "G:maj", "raw": "G", "t": "C:maj", "bar": 32, "beat": 2.0, "dur": 4.0}, {"chord": "D:maj", "raw": "D", "t": "G:maj", "bar": 33, "beat": 2.0, "dur": 2.0}, {"chord": "E:min", "raw": "Em", "t": "A:min", "bar": 34, "beat": 0.0, "dur": 2.0}, {"chord": "D:maj", "raw": "D", "t": "G:maj", "bar": 34, "beat": 2.0, "dur": 2.0}, {"chord": "C:maj", "raw": "C", "t": "F:maj", "bar": 35, "beat": 0.0, "dur": 2.0}, {"chord": "D:maj", "raw": "D", "t": "G:maj", "bar": 35, "beat": 2.0, "dur": 2.0}, {"chord": "E:min", "raw": "Em", "t": "A:min", "bar": 36, "beat": 0.0, "dur": 2.0}, {"chord": "D:maj", "raw": "D", "t": "G:maj", "bar": 36, "beat": 2.0, "dur": 2.0}, {"chord": "C:maj", "raw": "C", "t": "F:maj", "bar": 37, "beat": 0.0, "dur": 2.0}, {"chord": "D:maj", "raw": "D", "t": "G:maj", "bar": 37, "beat": 2.0, "dur": 2.0}, {"chord": "E:min", "raw": "Em", "t": "A:min", "bar": 38, "beat": 0.0, "dur": 2.0}, {"chord": "D:maj", "raw": "D", "t": "G:maj", "bar": 38, "beat": 2.0, "dur": 2.0}, {"chord": "C:maj", "raw": "C", "t": "F:maj", "bar": 39, "beat": 0.0, "dur": 2.0}, {"chord": "D:7", "raw": "D7", "t": "G:7", "bar": 39, "beat": 2.0, "dur": 2.0}, {"chord": "G:maj", "raw": "G", "t": "C:maj", "bar": 40, "beat": 0.0, "dur": 4.0}, {"chord": "D:maj", "raw": "D", "t": "G:maj", "bar": 41, "beat": 0.0, "dur": 4.0}, {"chord": "G:maj", "raw": "G", "t": "C:maj", "bar": 42, "beat": 0.0, "dur": 4.0}, {"chord": "G:7", "raw": "G7", "t": "C:7", "bar": 43, "beat": 0.0, "dur": 4.0}, {"chord": "C:maj", "raw": "C", "t": "F:maj", "bar": 44, "beat": 0.0, "dur": 6.0}, {"chord": "G:maj", "raw": "G", "t": "C:maj", "bar": 45, "beat": 2.0, "dur": 2.0}, {"chord": "D:maj", "raw": "D", "t": "G:maj", "bar": 46, "beat": 0.0, "dur": 2.0}, {"chord": "G:maj", "raw": "G", "t": "C:maj", "bar": 46, "beat": 2.0, "dur": 2.0}, {"chord": "C:maj", "raw": "C", "t": "F:maj", "bar": 47, "beat": 0.0, "dur": 2.0}, {"chord": "G:maj", "raw": "G", "t": "C:maj", "bar": 47, "beat": 2.0, "dur": 2.0}, {"chord": "D:maj", "raw": "D", "t": "G:maj", "bar": 48, "beat": 0.0, "dur": 2.0}, {"chord": "G:maj", "raw": "G", "t": "C:maj", "bar": 48, "beat": 2.0, "dur": 14.0}, {"chord": "C:maj", "raw": "C", "t": "F:maj", "bar": 52, "beat": 0.0, "dur": 1.0}, {"chord": "A:7", "raw": "A7", "t": "D:7", "bar": 52, "beat": 1.0, "dur": 1.0}, {"chord": "D:7", "raw": "D7", "t": "G:7", "bar": 52, "beat": 2.0, "dur": 2.0}, {"chord": "G:maj", "raw": "G", "t": "C:maj", "bar": 53, "beat": 0.0, "dur": 8.0}, {"chord": "C:maj", "raw": "C", "t": "F:maj", "bar": 55, "beat": 0.0, "dur": 2.0}, {"chord": "D:7", "raw": "D7", "t": "G:7", "bar": 55, "beat": 2.0, "dur": 2.0}, {"chord": "G:maj", "raw": "G", "t": "C:maj", "bar": 56, "beat": 0.0, "dur": 1.0}, {"chord": "D:maj", "raw": "D", "t": "G:maj", "bar": 56, "beat": 1.0, "dur": 1.0}, {"chord": "G:maj", "raw": "G", "t": "C:maj", "bar": 56, "beat": 2.0, "dur": 4.0}, {"chord": "D:maj", "raw": "D", "t": "G:maj", "bar": 57, "beat": 2.0, "dur": 2.0}, {"chord": "E:min", "raw": "Em", "t": "A:min", "bar": 58, "beat": 0.0, "dur": 2.0}, {"chord": "D:maj", "raw": "D", "t": "G:maj", "bar": 58, "beat": 2.0, "dur": 2.0}, {"chord": "C:maj", "raw": "C", "t": "F:maj", "bar": 59, "beat": 0.0, "dur": 2.0}, {"chord": "D:maj", "raw": "D", "t": "G:maj", "bar": 59, "beat": 2.0, "dur": 2.0}, {"chord": "E:min", "raw": "Em", "t": "A:min", "bar": 60, "beat": 0.0, "dur": 2.0}, {"chord": "D:maj", "raw": "D", "t": "G:maj", "bar": 60, "beat": 2.0, "dur": 2.0}, {"chord": "C:maj", "raw": "C", "t": "F:maj", "bar": 61, "beat": 0.0, "dur": 2.0}, {"chord": "D:maj", "raw": "D", "t": "G:maj", "bar": 61, "beat": 2.0, "dur": 2.0}, {"chord": "E:min", "raw": "Em", "t": "A:min", "bar": 62, "beat": 0.0, "dur": 2.0}, {"chord": "D:maj", "raw": "D", "t": "G:maj", "bar": 62, "beat": 2.0, "dur": 2.0}, {"chord": "C:maj", "raw": "C", "t": "F:maj", "bar": 63, "beat": 0.0, "dur": 2.0}, {"chord": "D:7", "raw": "D7", "t": "G:7", "bar": 63, "beat": 2.0, "dur": 2.0}, {"chord": "G:maj", "raw": "G", "t": "C:maj", "bar": 64, "beat": 0.0, "dur": 4.0}]}