{"source": "openbook", "song_id": "hallelujah_i_love_him_her_so", "title": "Hallelujah I Love Him (Her) So", "artist": "Ray Charles", "style": "Jazz", "key": "F major", "mode": "", "transpose_offset": -5, "bpm": null, "beats_per_bar": 4, "n_bars": 33, "bars": [{"bar": 0, "beats_per_bar": 4, "notes": [[72, 0.75, 0.25, 100], [74, 1.0, 0.75, 100], [72, 1.75, 0.25, 100], [68, 2.0, 0.75, 100], [67, 2.75, 0.25, 100], [65, 3.0, 0.75, 100], [62, 3.75, 0.25, 100]], "chords": [{"label": "F:maj", "raw": "F", "t": "C:maj", "onset": 0.0}, {"label": "F:maj", "raw": "F/A", "t": "C:maj", "onset": 2.0}], "next_chord": "Bb:maj", "next_chord_t": "F:maj"}, {"bar": 1, "beats_per_bar": 4, "notes": [[65, 0.0, 1.0, 100], [65, 1.0, 0.5, 100], [68, 1.5, 1.0, 100]], "chords": [{"label": "Bb:maj", "raw": "Bb", "t": "F:maj", "onset": 0.0}, {"label": "B:dim", "raw": "Bdim7", "t": "F#:dim", "onset": 2.0}, {"label": "C:7", "raw": "C7", "t": "G:7", "onset": 3.0}], "next_chord": "F:maj", "next_chord_t": "C:maj"}, {"bar": 2, "beats_per_bar": 4, "notes": [[72, 0.75, 0.25, 100], [74, 1.0, 0.75, 100], [72, 1.75, 0.25, 100], [68, 2.0, 0.75, 100], [67, 2.75, 0.25, 100], [65, 3.0, 0.75, 100], [62, 3.75, 0.25, 100]], "chords": [{"label": "F:maj", "raw": "F", "t": "C:maj", "onset": 0.0}, {"label": "F:maj", "raw": "F/A", "t": "C:maj", "onset": 2.0}], "next_chord": "Bb:maj", "next_chord_t": "F:maj"}, {"bar": 3, "beats_per_bar": 4, "notes": [[65, 0.0, 1.0, 100], [65, 1.0, 0.5, 100], [62, 1.5, 1.25, 100], [60, 2.75, 0.25, 100]], "chords": [{"label": "Bb:maj", "raw": "Bb", "t": "F:maj", "onset": 0.0}, {"label": "B:dim", "raw": "Bdim7", "t": "F#:dim", "onset": 2.0}, {"label": "C:7", "raw": "C7", "t": "G:7", "onset": 3.0}], "next_chord": "F:maj", "next_chord_t": "C:maj"}, {"bar": 4, "beats_per_bar": 4, "notes": [[74, 1.0, 0.75, 100], [72, 1.75, 0.25, 100], [68, 2.0, 0.75, 100], [67, 2.75, 0.25, 100], [65, 3.0, 0.75, 100], [62, 3.75, 0.25, 100]], "chords": [{"label": "F:maj", "raw": "F", "t": "C:maj", "onset": 0.0}], "next_chord": "F:7", "next_chord_t": "C:7"}, {"bar": 5, "beats_per_bar": 4, "notes": [[65, 0.0, 1.0, 100], [65, 1.0, 0.5, 100], [65, 1.5, 1.0, 100]], "chords": [{"label": "F:7", "raw": "F7", "t": "C:7", "onset": 0.0}, {"label": "F:7", "raw": "F7#5", "t": "C:7", "onset": 3.0}], "next_chord": "Bb:maj", "next_chord_t": "F:maj"}, {"bar": 6, "beats_per_bar": 4, "notes": [[62, 0.75, 0.25, 100], [65, 1.0, 0.75, 100], [62, 1.75, 0.25, 100], [65, 2.0, 0.75, 100], [62, 2.75, 0.25, 100], [65, 3.0, 0.75, 100], [62, 3.75, 0.25, 100]], "chords": [{"label": "Bb:maj", "raw": "Bb", "t": "F:maj", "onset": 0.0}], "next_chord": "B:dim", "next_chord_t": "F#:dim"}, {"bar": 7, "beats_per_bar": 4, "notes": [[65, 0.0, 1.0, 100], [65, 1.0, 0.5, 100], [65, 1.5, 1.25, 100], [60, 2.75, 0.25, 100], [62, 3.0, 0.75, 100], [65, 3.75, 0.25, 100]], "chords": [{"label": "B:dim", "raw": "Bdim7", "t": "F#:dim", "onset": 0.0}], "next_chord": "F:maj", "next_chord_t": "C:maj"}, {"bar": 8, "beats_per_bar": 4, "notes": [[69, 0.0, 0.5, 100], [72, 0.5, 1.5, 100], [69, 3.0, 0.75, 100], [69, 3.75, 0.25, 100]], "chords": [{"label": "F:maj", "raw": "F", "t": "C:maj", "onset": 0.0}, {"label": "A:7", "raw": "A7", "t": "E:7", "onset": 2.0}], "next_chord": "D:min", "next_chord_t": "A:min"}, {"bar": 9, "beats_per_bar": 4, "notes": [[67, 0.0, 0.5, 100], [65, 0.5, 1.5, 100], [68, 3.0, 0.75, 100], [67, 3.75, 0.25, 100]], "chords": [{"label": "D:min", "raw": "Dm", "t": "A:min", "onset": 0.0}, {"label": "Bb:7", "raw": "Bb7", "t": "F:7", "onset": 2.0}], "next_chord": "G:7", "next_chord_t": "D:7"}, {"bar": 10, "beats_per_bar": 4, "notes": [[68, 0.0, 0.75, 100], [67, 0.75, 0.25, 100], [65, 1.0, 0.75, 100], [62, 1.75, 0.25, 100], [65, 2.0, 1.0, 100], [65, 3.0, 0.5, 100], [65, 3.5, 1.0, 100]], "chords": [{"label": "G:7", "raw": "G7", "t": "D:7", "onset": 0.0}, {"label": "C:7", "raw": "C7(11)", "t": "G:7", "onset": 2.0}], "next_chord": "F:maj", "next_chord_t": "C:maj"}, {"bar": 11, "beats_per_bar": 4, "notes": [], "chords": [{"label": "F:maj", "raw": "F", "t": "C:maj", "onset": 0.0}], "next_chord": "Bb:maj", "next_chord_t": "F:maj"}, {"bar": 12, "beats_per_bar": 4, "notes": [[62, 0.75, 0.25, 100], [65, 1.0, 0.75, 100], [62, 1.75, 0.25, 100], [65, 2.0, 0.75, 100], [62, 2.75, 0.25, 100], [65, 3.0, 0.75, 100], [62, 3.75, 0.25, 100]], "chords": [{"label": "Bb:maj", "raw": "Bb6", "t": "F:maj", "onset": 0.0}], "next_chord": "B:dim", "next_chord_t": "F#:dim"}, {"bar": 13, "beats_per_bar": 4, "notes": [[65, 0.0, 0.75, 100], [65, 0.75, 0.25, 100], [65, 1.0, 1.0, 100]], "chords": [{"label": "B:dim", "raw": "Bdim7", "t": "F#:dim", "onset": 0.0}], "next_chord": "F:maj", "next_chord_t": "C:maj"}, {"bar": 14, "beats_per_bar": 4, "notes": [[69, 1.0, 1.0, 100], [74, 2.0, 0.75, 100], [72, 2.75, 0.25, 100], [69, 3.0, 0.75, 100], [65, 3.75, 0.25, 100]], "chords": [{"label": "F:maj", "raw": "F", "t": "C:maj", "onset": 0.0}], "next_chord": "F:7", "next_chord_t": "C:7"}, {"bar": 15, "beats_per_bar": 4, "notes": [[69, 0.0, 1.0, 100], [65, 1.0, 0.5, 100], [67, 1.5, 1.5, 100]], "chords": [{"label": "F:7", "raw": "F7", "t": "C:7", "onset": 0.0}], "next_chord": "Bb:7", "next_chord_t": "F:7"}, {"bar": 16, "beats_per_bar": 4, "notes": [[65, 1.0, 0.75, 100], [62, 1.75, 0.25, 100], [65, 2.0, 0.75, 100], [62, 2.75, 0.25, 100], [65, 3.0, 0.75, 100], [62, 3.75, 0.25, 100]], "chords": [{"label": "Bb:7", "raw": "Bb9", "t": "F:7", "onset": 0.0}], "next_chord": "Ab:7", "next_chord_t": "Eb:7"}, {"bar": 17, "beats_per_bar": 4, "notes": [[65, 0.0, 1.0, 100], [65, 1.0, 0.5, 100], [65, 1.5, 1.0, 100]], "chords": [{"label": "Ab:7", "raw": "Ab9", "t": "Eb:7", "onset": 0.0}], "next_chord": "G:7", "next_chord_t": "D:7"}, {"bar": 18, "beats_per_bar": 4, "notes": [[62, 0.75, 0.25, 100], [67, 1.0, 0.75, 100], [62, 1.75, 0.25, 100]], "chords": [{"label": "G:7", "raw": "G7", "t": "D:7", "onset": 0.0}], "next_chord": "C:7", "next_chord_t": "G:7"}, {"bar": 19, "beats_per_bar": 4, "notes": [[67, 0.0, 0.5, 100], [69, 0.5, 1.0, 100], [74, 1.5, 1.5, 100], [72, 3.0, 1.0, 100]], "chords": [{"label": "C:7", "raw": "C7", "t": "G:7", "onset": 0.0}], "next_chord": "F:maj", "next_chord_t": "C:maj"}, {"bar": 20, "beats_per_bar": 4, "notes": [[74, 1.0, 0.75, 100], [72, 1.75, 0.25, 100], [68, 2.0, 0.75, 100], [67, 2.75, 0.25, 100], [65, 3.0, 0.75, 100], [62, 3.75, 0.25, 100]], "chords": [{"label": "F:maj", "raw": "F", "t": "C:maj", "onset": 0.0}, {"label": "F:maj", "raw": "F/A", "t": "C:maj", "onset": 2.0}], "next_chord": "Bb:maj", "next_chord_t": "F:maj"}, {"bar": 21, "beats_per_bar": 4, "notes": [[65, 0.0, 1.0, 100], [65, 1.0, 0.5, 100], [68, 1.5, 1.0, 100]], "chords": [{"label": "Bb:maj", "raw": "Bb", "t": "F:maj", "onset": 0.0}, {"label": "B:dim", "raw": "Bdim7", "t": "F#:dim", "onset": 2.0}, {"label": "C:7", "raw": "C7", "t": "G:7", "onset": 3.0}], "next_chord": "F:maj", "next_chord_t": "C:maj"}, {"bar": 22, "beats_per_bar": 4, "notes": [[74, 1.0, 0.75, 100], [72, 1.75, 0.25, 100], [68, 2.0, 0.75, 100], [67, 2.75, 0.25, 100], [65, 3.0, 0.75, 100], [62, 3.75, 0.25, 100]], "chords": [{"label": "F:maj", "raw": "F", "t": "C:maj", "onset": 0.0}, {"label": "F:maj", "raw": "F/A", "t": "C:maj", "onset": 2.0}], "next_chord": "Bb:maj", "next_chord_t": "F:maj"}, {"bar": 23, "beats_per_bar": 4, "notes": [[65, 0.0, 1.0, 100], [65, 1.0, 0.5, 100], [62, 1.5, 1.25, 100], [60, 2.75, 0.25, 100]], "chords": [{"label": "Bb:maj", "raw": "Bb", "t": "F:maj", "onset": 0.0}, {"label": "B:dim", "raw": "Bdim7", "t": "F#:dim", "onset": 2.0}, {"label": "C:7", "raw": "C7", "t": "G:7", "onset": 3.0}], "next_chord": "F:maj", "next_chord_t": "C:maj"}, {"bar": 24, "beats_per_bar": 4, "notes": [[72, 0.75, 0.25, 100], [74, 1.0, 0.75, 100], [72, 1.75, 0.25, 100], [68, 2.0, 0.75, 100], [67, 2.75, 0.25, 100], [65, 3.0, 0.75, 100], [62, 3.75, 0.25, 100]], "chords": [{"label": "F:maj", "raw": "F", "t": "C:maj", "onset": 0.0}], "next_chord": "F:7", "next_chord_t": "C:7"}, {"bar": 25, "beats_per_bar": 4, "notes": [[65, 0.0, 1.0, 100], [65, 1.0, 0.5, 100], [65, 1.5, 1.0, 100]], "chords": [{"label": "F:7", "raw": "F7", "t": "C:7", "onset": 0.0}, {"label": "F:7", "raw": "F7#5", "t": "C:7", "onset": 3.0}], "next_chord": "Bb:maj", "next_chord_t": "F:maj"}, {"bar": 26, "beats_per_bar": 4, "notes": [[62, 0.75, 0.25, 100], [65, 1.0, 0.75, 100], [62, 1.75, 0.25, 100], [65, 2.0, 0.75, 100], [62, 2.75, 0.25, 100], [65, 3.0, 0.75, 100], [62, 3.75, 0.25, 100]], "chords": [{"label": "Bb:maj", "raw": "Bb", "t": "F:maj", "onset": 0.0}], "next_chord": "B:dim", "next_chord_t": "F#:dim"}, {"bar": 27, "beats_per_bar": 4, "notes": [[65, 0.0, 1.0, 100], [65, 1.0, 0.5, 100], [65, 1.5, 1.25, 100], [60, 2.75, 0.25, 100], [62, 3.0, 0.75, 100], [65, 3.75, 0.25, 100]], "chords": [{"label": "B:dim", "raw": "Bdim7", "t": "F#:dim", "onset": 0.0}], "next_chord": "F:maj", "next_chord_t": "C:maj"}, {"bar": 28, "beats_per_bar": 4, "notes": [[69, 0.0, 0.5, 100], [72, 0.5, 1.5, 100], [69, 3.0, 0.75, 100], [69, 3.75, 0.25, 100]], "chords": [{"label": "F:maj", "raw": "F", "t": "C:maj", "onset": 0.0}, {"label": "A:7", "raw": "A7", "t": "E:7", "onset": 2.0}], "next_chord": "D:min", "next_chord_t": "A:min"}, {"bar": 29, "beats_per_bar": 4, "notes": [[67, 0.0, 0.5, 100], [65, 0.5, 1.5, 100], [68, 3.0, 0.75, 100], [67, 3.75, 0.25, 100]], "chords": [{"label": "D:min", "raw": "Dm", "t": "A:min", "onset": 0.0}, {"label": "Bb:7", "raw": "Bb7", "t": "F:7", "onset": 2.0}], "next_chord": "G:7", "next_chord_t": "D:7"}, {"bar": 30, "beats_per_bar": 4, "notes": [[68, 0.0, 0.75, 100], [67, 0.75, 0.25, 100], [65, 1.0, 0.75, 100], [62, 1.75, 0.25, 100], [65, 2.0, 1.0, 100], [65, 3.0, 0.5, 100], [65, 3.5, 6.5, 100]], "chords": [{"label": "G:7", "raw": "G7", "t": "D:7", "onset": 0.0}, {"label": "C:7", "raw": "C7(11)", "t": "G:7", "onset": 2.0}], "next_chord": "F:maj", "next_chord_t": "C:maj"}, {"bar": 31, "beats_per_bar": 4, "notes": [], "chords": [{"label": "F:maj", "raw": "F", "t": "C:maj", "onset": 0.0}, {"label": "Bb:7", "raw": "Bb7", "t": "F:7", "onset": 2.0}], "next_chord": "F:maj", "next_chord_t": "C:maj"}, {"bar": 32, "beats_per_bar": 4, "notes": [], "chords": [{"label": "F:maj", "raw": "F", "t": "C:maj", "onset": 0.0}], "next_chord": null, "next_chord_t": null}], "chord_sequence": [{"chord": "F:maj", "raw": "F", "t": "C:maj", "bar": 0, "beat": 0.0, "dur": 4.0}, {"chord": "Bb:maj", "raw": "Bb", "t": "F:maj", "bar": 1, "beat": 0.0, "dur": 2.0}, {"chord": "B:dim", "raw": "Bdim", "t": "F#:dim", "bar": 1, "beat": 2.0, "dur": 1.0}, {"chord": "C:7", "raw": "C7", "t": "G:7", "bar": 1, "beat": 3.0, "dur": 1.0}, {"chord": "F:maj", "raw": "F", "t": "C:maj", "bar": 2, "beat": 0.0, "dur": 4.0}, {"chord": "Bb:maj", "raw": "Bb", "t": "F:maj", "bar": 3, "beat": 0.0, "dur": 2.0}, {"chord": "B:dim", "raw": "Bdim", "t": "F#:dim", "bar": 3, "beat": 2.0, "dur": 1.0}, {"chord": "C:7", "raw": "C7", "t": "G:7", "bar": 3, "beat": 3.0, "dur": 1.0}, {"chord": "F:maj", "raw": "F", "t": "C:maj", "bar": 4, "beat": 0.0, "dur": 4.0}, {"chord": "F:7", "raw": "F7", "t": "C:7", "bar": 5, "beat": 0.0, "dur": 4.0}, {"chord": "Bb:maj", "raw": "Bb", "t": "F:maj", "bar": 6, "beat": 0.0, "dur": 4.0}, {"chord": "B:dim", "raw": "Bdim", "t": "F#:dim", "bar": 7, "beat": 0.0, "dur": 4.0}, {"chord": "F:maj", "raw": "F", "t": "C:maj", "bar": 8, "beat": 0.0, "dur": 2.0}, {"chord": "A:7", "raw": "A7", "t": "E:7", "bar": 8, "beat": 2.0, "dur": 2.0}, {"chord": "D:min", "raw": "Dm", "t": "A:min", "bar": 9, "beat": 0.0, "dur": 2.0}, {"chord": "Bb:7", "raw": "Bb7", "t": "F:7", "bar": 9, "beat": 2.0, "dur": 2.0}, {"chord": "G:7", "raw": "G7", "t": "D:7", "bar": 10, "beat": 0.0, "dur": 2.0}, {"chord": "C:7", "raw": "C7", "t": "G:7", "bar": 10, "beat": 2.0, "dur": 2.0}, {"chord": "F:maj", "raw": "F", "t": "C:maj", "bar": 11, "beat": 0.0, "dur": 4.0}, {"chord": "Bb:maj", "raw": "Bb", "t": "F:maj", "bar": 12, "beat": 0.0, "dur": 4.0}, {"chord": "B:dim", "raw": "Bdim", "t": "F#:dim", "bar": 13, "beat": 0.0, "dur": 4.0}, {"chord": "F:maj", "raw": "F", "t": "C:maj", "bar": 14, "beat": 0.0, "dur": 4.0}, {"chord": "F:7", "raw": "F7", "t": "C:7", "bar": 15, "beat": 0.0, "dur": 4.0}, {"chord": "Bb:7", "raw": "Bb7", "t": "F:7", "bar": 16, "beat": 0.0, "dur": 4.0}, {"chord": "Ab:7", "raw": "Ab7", "t": "Eb:7", "bar": 17, "beat": 0.0, "dur": 4.0}, {"chord": "G:7", "raw": "G7", "t": "D:7", "bar": 18, "beat": 0.0, "dur": 4.0}, {"chord": "C:7", "raw": "C7", "t": "G:7", "bar": 19, "beat": 0.0, "dur": 4.0}, {"chord": "F:maj", "raw": "F", "t": "C:maj", "bar": 20, "beat": 0.0, "dur": 4.0}, {"chord": "Bb:maj", "raw": "Bb", "t": "F:maj", "bar": 21, "beat": 0.0, "dur": 2.0}, {"chord": "B:dim", "raw": "Bdim", "t": "F#:dim", "bar": 21, "beat": 2.0, "dur": 1.0}, {"chord": "C:7", "raw": "C7", "t": "G:7", "bar": 21, "beat": 3.0, "dur": 1.0}, {"chord": "F:maj", "raw": "F", "t": "C:maj", "bar": 22, "beat": 0.0, "dur": 4.0}, {"chord": "Bb:maj", "raw": "Bb", "t": "F:maj", "bar": 23, "beat": 0.0, "dur": 2.0}, {"chord": "B:dim", "raw": "Bdim", "t": "F#:dim", "bar": 23, "beat": 2.0, "dur": 1.0}, {"chord": "C:7", "raw": "C7", "t": "G:7", "bar": 23, "beat": 3.0, "dur": 1.0}, {"chord": "F:maj", "raw": "F", "t": "C:maj", "bar": 24, "beat": 0.0, "dur": 4.0}, {"chord": "F:7", "raw": "F7", "t": "C:7", "bar": 25, "beat": 0.0, "dur": 4.0}, {"chord": "Bb:maj", "raw": "Bb", "t": "F:maj", "bar": 26, "beat": 0.0, "dur": 4.0}, {"chord": "B:dim", "raw": "Bdim", "t": "F#:dim", "bar": 27, "beat": 0.0, "dur": 4.0}, {"chord": "F:maj", "raw": "F", "t": "C:maj", "bar": 28, "beat": 0.0, "dur": 2.0}, {"chord": "A:7", "raw": "A7", "t": "E:7", "bar": 28, "beat": 2.0, "dur": 2.0}, {"chord": "D:min", "raw": "Dm", "t": "A:min", "bar": 29, "beat": 0.0, "dur": 2.0}, {"chord": "Bb:7", "raw": "Bb7", "t": "F:7", "bar": 29, "beat": 2.0, "dur": 2.0}, {"chord": "G:7", "raw": "G7", "t": "D:7", "bar": 30, "beat": 0.0, "dur": 2.0}, {"chord": "C:7", "raw": "C7", "t": "G:7", "bar": 30, "beat": 2.0, "dur": 2.0}, {"chord": "F:maj", "raw": "F", "t": "C:maj", "bar": 31, "beat": 0.0, "dur": 2.0}, {"chord": "Bb:7", "raw": "Bb7", "t": "F:7", "bar": 31, "beat": 2.0, "dur": 2.0}, {"chord": "F:maj", "raw": "F", "t": "C:maj", "bar": 32, "beat": 0.0, "dur": 4.0}]}