{"source": "pop909", "song_id": "537", "title": "朋友别哭", "artist": "吕方", "style": "pop", "key": "F:maj", "mode": "", "transpose_offset": -5, "bpm": 75.0, "beats_per_bar": 4, "n_bars": 75, "bars": [{"bar": 0, "beats_per_bar": 4, "notes": [], "chords": [{"label": "F:sus2", "raw": "F:sus2", "t": "C:sus2", "onset": 0.0}, {"label": "F:maj", "raw": "F:maj", "t": "C:maj", "onset": 2.0}], "next_chord": "F:maj", "next_chord_t": "C:maj"}, {"bar": 1, "beats_per_bar": 4, "notes": [], "chords": [{"label": "F:maj", "raw": "F:maj/3", "t": "C:maj", "onset": 0.0}], "next_chord": "D:maj", "next_chord_t": "A:maj"}, {"bar": 2, "beats_per_bar": 4, "notes": [], "chords": [{"label": "D:maj", "raw": "D:maj", "t": "A:maj", "onset": 0.0}], "next_chord": "G:min", "next_chord_t": "D:min"}, {"bar": 3, "beats_per_bar": 4, "notes": [], "chords": [{"label": "G:min", "raw": "G:min", "t": "D:min", "onset": 0.0}], "next_chord": "C:sus4", "next_chord_t": "G:sus4"}, {"bar": 4, "beats_per_bar": 4, "notes": [], "chords": [{"label": "C:sus4", "raw": "C:sus4", "t": "G:sus4", "onset": 0.0}], "next_chord": "C:maj", "next_chord_t": "G:maj"}, {"bar": 5, "beats_per_bar": 4, "notes": [[60, 3.25, 0.5, 104], [62, 3.75, 0.5, 102]], "chords": [{"label": "C:maj", "raw": "C:maj", "t": "G:maj", "onset": 0.0}], "next_chord": "F:sus2", "next_chord_t": "C:sus2"}, {"bar": 6, "beats_per_bar": 4, "notes": [[69, 0.25, 1.0, 114], [69, 1.25, 0.5, 110], [67, 1.75, 0.25, 100], [69, 2.0, 1.75, 107], [67, 3.75, 0.25, 104], [69, 4.0, 0.25, 93]], "chords": [{"label": "F:sus2", "raw": "F:sus2", "t": "C:sus2", "onset": 0.0}, {"label": "G:sus2", "raw": "G:sus2", "t": "D:sus2", "onset": 3.0}], "next_chord": "A:min", "next_chord_t": "E:min"}, {"bar": 7, "beats_per_bar": 4, "notes": [[72, 0.25, 1.0, 113], [72, 1.25, 0.5, 108], [74, 1.75, 0.25, 113], [72, 2.0, 1.75, 91], [69, 3.75, 0.25, 107], [72, 4.0, 0.25, 100]], "chords": [{"label": "A:min", "raw": "A:min", "t": "E:min", "onset": 0.0}], "next_chord": "D:min", "next_chord_t": "A:min"}, {"bar": 8, "beats_per_bar": 4, "notes": [[74, 0.25, 1.0, 116], [74, 1.25, 0.5, 119], [72, 1.75, 0.25, 113], [74, 2.0, 0.75, 117], [72, 2.75, 0.5, 104], [69, 3.25, 0.25, 104], [67, 3.5, 0.5, 102], [65, 4.0, 0.25, 108]], "chords": [{"label": "D:min", "raw": "D:min", "t": "A:min", "onset": 0.0}], "next_chord": "G:sus4", "next_chord_t": "D:sus4"}, {"bar": 9, "beats_per_bar": 4, "notes": [[67, 0.25, 1.5, 107], [69, 1.75, 0.5, 108], [67, 2.25, 1.5, 113], [69, 3.75, 0.25, 107], [67, 4.0, 0.25, 100]], "chords": [{"label": "G:sus4", "raw": "G:sus4", "t": "D:sus4", "onset": 0.0}], "next_chord": "D:min", "next_chord_t": "A:min"}, {"bar": 10, "beats_per_bar": 4, "notes": [[65, 0.25, 1.0, 107], [65, 1.25, 0.5, 113], [67, 1.75, 0.25, 113], [69, 2.0, 1.75, 108], [74, 3.75, 0.25, 110], [77, 4.0, 0.25, 113]], "chords": [{"label": "D:min", "raw": "D:min", "t": "A:min", "onset": 0.0}], "next_chord": "A:min", "next_chord_t": "E:min"}, {"bar": 11, "beats_per_bar": 4, "notes": [[76, 0.25, 1.0, 119], [76, 1.25, 0.5, 114], [74, 1.75, 0.25, 108], [72, 2.0, 1.75, 102], [72, 3.75, 0.25, 102], [69, 4.0, 0.25, 102]], "chords": [{"label": "A:min", "raw": "A:min", "t": "E:min", "onset": 0.0}], "next_chord": "G:min", "next_chord_t": "D:min"}, {"bar": 12, "beats_per_bar": 4, "notes": [[67, 0.25, 1.5, 108], [67, 1.75, 0.25, 107], [69, 2.0, 0.25, 108], [67, 2.25, 1.5, 114], [65, 3.75, 0.5, 110]], "chords": [{"label": "G:min", "raw": "G:min", "t": "D:min", "onset": 0.0}], "next_chord": "C:sus4", "next_chord_t": "G:sus4"}, {"bar": 13, "beats_per_bar": 4, "notes": [[67, 0.25, 3.0, 116], [60, 3.25, 0.5, 104], [62, 3.75, 0.5, 102]], "chords": [{"label": "C:sus4", "raw": "C:sus4", "t": "G:sus4", "onset": 0.0}, {"label": "C:maj", "raw": "C:maj", "t": "G:maj", "onset": 2.0}], "next_chord": "F:maj", "next_chord_t": "C:maj"}, {"bar": 14, "beats_per_bar": 4, "notes": [[69, 0.25, 1.0, 114], [69, 1.25, 0.5, 110], [67, 1.75, 0.25, 100], [69, 2.0, 1.75, 107], [67, 3.75, 0.25, 104], [69, 4.0, 0.25, 93]], "chords": [{"label": "F:maj", "raw": "F:maj", "t": "C:maj", "onset": 0.0}, {"label": "F:sus2", "raw": "F:sus2", "t": "C:sus2", "onset": 1.0}, {"label": "F:maj", "raw": "F:maj", "t": "C:maj", "onset": 3.0}], "next_chord": "A:min", "next_chord_t": "E:min"}, {"bar": 15, "beats_per_bar": 4, "notes": [[72, 0.25, 1.0, 113], [72, 1.25, 0.5, 108], [74, 1.75, 0.25, 113], [72, 2.0, 1.75, 91], [69, 3.75, 0.25, 107], [72, 4.0, 0.25, 100]], "chords": [{"label": "A:min", "raw": "A:min", "t": "E:min", "onset": 0.0}], "next_chord": "A:min", "next_chord_t": "E:min"}, {"bar": 16, "beats_per_bar": 4, "notes": [[74, 0.25, 1.0, 116], [74, 1.25, 0.5, 119], [72, 1.75, 0.25, 113], [74, 2.0, 0.75, 117], [72, 2.75, 0.5, 104], [69, 3.25, 0.25, 104], [67, 3.5, 0.5, 102], [65, 4.0, 0.25, 108]], "chords": [{"label": "A:min", "raw": "A:min", "t": "E:min", "onset": 0.0}, {"label": "D:min", "raw": "D:min", "t": "A:min", "onset": 0.0}, {"label": "D:min7", "raw": "D:min7/b7", "t": "A:min7", "onset": 2.0}, {"label": "C:maj", "raw": "C:maj", "t": "G:maj", "onset": 3.0}], "next_chord": "G:min", "next_chord_t": "D:min"}, {"bar": 17, "beats_per_bar": 4, "notes": [[67, 0.25, 1.5, 107], [69, 1.75, 0.5, 108], [67, 2.25, 1.5, 113], [69, 3.75, 0.25, 107], [67, 4.0, 0.25, 100]], "chords": [{"label": "G:min", "raw": "G:min", "t": "D:min", "onset": 0.0}, {"label": "C:sus2", "raw": "C:sus2", "t": "G:sus2", "onset": 2.0}], "next_chord": "D:min", "next_chord_t": "A:min"}, {"bar": 18, "beats_per_bar": 4, "notes": [[65, 0.25, 1.0, 107], [65, 1.25, 0.5, 113], [67, 1.75, 0.25, 113], [69, 2.0, 1.75, 108], [74, 3.75, 0.25, 110], [77, 4.0, 0.25, 113]], "chords": [{"label": "D:min", "raw": "D:min", "t": "A:min", "onset": 0.0}], "next_chord": "D:min", "next_chord_t": "A:min"}, {"bar": 19, "beats_per_bar": 4, "notes": [[76, 0.25, 1.0, 119], [76, 1.25, 0.5, 114], [74, 1.75, 0.25, 108], [72, 2.0, 1.75, 102], [72, 3.75, 0.25, 102], [69, 4.0, 0.25, 102]], "chords": [{"label": "D:min", "raw": "D:min", "t": "A:min", "onset": 0.0}, {"label": "A:min", "raw": "A:min", "t": "E:min", "onset": 0.0}], "next_chord": "A:min", "next_chord_t": "E:min"}, {"bar": 20, "beats_per_bar": 4, "notes": [[67, 0.25, 1.5, 108], [67, 1.75, 0.25, 107], [69, 2.0, 0.25, 108], [67, 2.25, 0.5, 114], [65, 2.75, 0.5, 113], [62, 3.25, 0.25, 107], [65, 3.5, 0.75, 113]], "chords": [{"label": "A:min", "raw": "A:min", "t": "E:min", "onset": 0.0}, {"label": "G:min", "raw": "G:min", "t": "D:min", "onset": 0.0}, {"label": "C:maj", "raw": "C:maj", "t": "G:maj", "onset": 2.0}], "next_chord": "F:maj", "next_chord_t": "C:maj"}, {"bar": 21, "beats_per_bar": 4, "notes": [[65, 0.25, 3.0, 114], [65, 3.25, 0.25, 116], [67, 3.5, 0.5, 116], [69, 4.0, 0.25, 116]], "chords": [{"label": "F:maj", "raw": "F:maj", "t": "C:maj", "onset": 0.0}], "next_chord": "F:maj", "next_chord_t": "C:maj"}, {"bar": 22, "beats_per_bar": 4, "notes": [[72, 0.25, 1.75, 114], [72, 2.0, 0.25, 114], [74, 2.25, 0.5, 117], [72, 2.75, 0.5, 116], [69, 3.25, 0.5, 113], [67, 3.75, 0.5, 116]], "chords": [{"label": "F:maj", "raw": "F:maj", "t": "C:maj", "onset": 0.0}], "next_chord": "D:min", "next_chord_t": "A:min"}, {"bar": 23, "beats_per_bar": 4, "notes": [[69, 0.25, 0.5, 114], [69, 0.75, 0.5, 110], [69, 1.25, 0.25, 113], [67, 1.5, 0.5, 110], [65, 2.0, 1.25, 107], [65, 3.25, 0.25, 116], [67, 3.5, 0.5, 114], [69, 4.0, 0.25, 114]], "chords": [{"label": "D:min", "raw": "D:min", "t": "A:min", "onset": 0.0}], "next_chord": "Bb:maj", "next_chord_t": "F:maj"}, {"bar": 24, "beats_per_bar": 4, "notes": [[77, 0.25, 1.75, 117], [77, 2.0, 0.25, 114], [79, 2.25, 0.5, 116], [77, 2.75, 0.5, 110], [74, 3.25, 0.25, 113], [72, 3.5, 0.5, 107], [69, 4.0, 0.25, 113]], "chords": [{"label": "Bb:maj", "raw": "Bb:maj", "t": "F:maj", "onset": 0.0}, {"label": "C:maj", "raw": "C:maj", "t": "G:maj", "onset": 2.0}], "next_chord": "C:maj", "next_chord_t": "G:maj"}, {"bar": 25, "beats_per_bar": 4, "notes": [[72, 0.25, 3.0, 117], [72, 3.25, 0.5, 117], [74, 3.75, 0.5, 119]], "chords": [{"label": "C:maj", "raw": "C:maj", "t": "G:maj", "onset": 0.0}, {"label": "F:maj", "raw": "F:maj", "t": "C:maj", "onset": 0.0}], "next_chord": "F:maj", "next_chord_t": "C:maj"}, {"bar": 26, "beats_per_bar": 4, "notes": [[77, 0.0, 1.5, 123], [79, 1.5, 0.5, 117], [79, 2.0, 0.5, 114], [77, 2.5, 0.5, 119], [74, 3.0, 0.5, 117], [72, 3.5, 0.25, 116], [74, 3.75, 0.75, 117]], "chords": [{"label": "F:maj", "raw": "F:maj", "t": "C:maj", "onset": 0.0}], "next_chord": "D:min", "next_chord_t": "A:min"}, {"bar": 27, "beats_per_bar": 4, "notes": [[74, 0.5, 0.5, 114], [74, 1.0, 0.25, 113], [72, 1.25, 0.5, 114], [69, 1.75, 1.25, 113], [72, 3.0, 0.5, 114], [69, 3.5, 0.5, 119]], "chords": [{"label": "D:min", "raw": "D:min", "t": "A:min", "onset": 0.0}], "next_chord": "G:min", "next_chord_t": "D:min"}, {"bar": 28, "beats_per_bar": 4, "notes": [[67, 0.0, 1.5, 119], [67, 1.5, 0.25, 117], [69, 1.75, 0.25, 114], [67, 2.0, 1.5, 119], [62, 3.5, 0.5, 116]], "chords": [{"label": "G:min", "raw": "G:min", "t": "D:min", "onset": 0.0}, {"label": "C:maj", "raw": "C:maj", "t": "G:maj", "onset": 2.0}], "next_chord": "F:maj", "next_chord_t": "C:maj"}, {"bar": 29, "beats_per_bar": 4, "notes": [[65, 0.0, 2.25, 119]], "chords": [{"label": "F:maj", "raw": "F:maj", "t": "C:maj", "onset": 0.0}], "next_chord": "F:maj", "next_chord_t": "C:maj"}, {"bar": 30, "beats_per_bar": 4, "notes": [], "chords": [{"label": "F:maj", "raw": "F:maj", "t": "C:maj", "onset": 0.0}, {"label": "F:sus2", "raw": "F:sus2", "t": "C:sus2", "onset": 0.0}, {"label": "F:maj", "raw": "F:maj", "t": "C:maj", "onset": 2.0}], "next_chord": "F:maj", "next_chord_t": "C:maj"}, {"bar": 31, "beats_per_bar": 4, "notes": [], "chords": [{"label": "F:maj", "raw": "F:maj", "t": "C:maj", "onset": 0.0}], "next_chord": "D:maj", "next_chord_t": "A:maj"}, {"bar": 32, "beats_per_bar": 4, "notes": [], "chords": [{"label": "D:maj", "raw": "D:maj", "t": "A:maj", "onset": 0.0}], "next_chord": "D:min", "next_chord_t": "A:min"}, {"bar": 33, "beats_per_bar": 4, "notes": [], "chords": [{"label": "D:min", "raw": "D:min", "t": "A:min", "onset": 0.0}], "next_chord": "Bb:maj", "next_chord_t": "F:maj"}, {"bar": 34, "beats_per_bar": 4, "notes": [], "chords": [{"label": "Bb:maj", "raw": "Bb:maj", "t": "F:maj", "onset": 0.0}], "next_chord": "Bb:maj", "next_chord_t": "F:maj"}, {"bar": 35, "beats_per_bar": 4, "notes": [], "chords": [{"label": "Bb:maj", "raw": "Bb:maj", "t": "F:maj", "onset": 0.0}, {"label": "A:min", "raw": "A:min", "t": "E:min", "onset": 0.0}, {"label": "D:min", "raw": "D:min", "t": "A:min", "onset": 2.0}], "next_chord": "G:min", "next_chord_t": "D:min"}, {"bar": 36, "beats_per_bar": 4, "notes": [], "chords": [{"label": "G:min", "raw": "G:min", "t": "D:min", "onset": 0.0}], "next_chord": "C:maj", "next_chord_t": "G:maj"}, {"bar": 37, "beats_per_bar": 4, "notes": [], "chords": [{"label": "C:maj", "raw": "C:maj", "t": "G:maj", "onset": 0.0}], "next_chord": "C:maj", "next_chord_t": "G:maj"}, {"bar": 38, "beats_per_bar": 4, "notes": [[60, 3.0, 0.5, 104], [62, 3.5, 0.5, 102]], "chords": [{"label": "C:maj", "raw": "C:maj", "t": "G:maj", "onset": 0.0}], "next_chord": "F:maj", "next_chord_t": "C:maj"}, {"bar": 39, "beats_per_bar": 4, "notes": [[69, 0.0, 1.0, 114], [69, 1.0, 0.5, 110], [67, 1.5, 0.25, 100], [69, 1.75, 1.75, 107], [67, 3.5, 0.25, 104], [69, 3.75, 0.25, 93]], "chords": [{"label": "F:maj", "raw": "F:maj", "t": "C:maj", "onset": 0.0}, {"label": "F:sus2", "raw": "F:sus2", "t": "C:sus2", "onset": 1.0}, {"label": "F:maj", "raw": "F:maj", "t": "C:maj", "onset": 3.0}], "next_chord": "A:min", "next_chord_t": "E:min"}, {"bar": 40, "beats_per_bar": 4, "notes": [[72, 0.0, 1.0, 113], [72, 1.0, 0.5, 108], [74, 1.5, 0.25, 113], [72, 1.75, 1.75, 91], [69, 3.5, 0.25, 107], [72, 3.75, 0.25, 100]], "chords": [{"label": "A:min", "raw": "A:min", "t": "E:min", "onset": 0.0}], "next_chord": "D:min", "next_chord_t": "A:min"}, {"bar": 41, "beats_per_bar": 4, "notes": [[74, 0.0, 1.0, 116], [74, 1.0, 0.5, 119], [72, 1.5, 0.25, 113], [74, 1.75, 0.75, 117], [72, 2.5, 0.5, 104], [69, 3.0, 0.25, 104], [67, 3.25, 0.5, 102], [65, 3.75, 0.25, 108]], "chords": [{"label": "D:min", "raw": "D:min", "t": "A:min", "onset": 0.0}, {"label": "D:min7", "raw": "D:min7/b7", "t": "A:min7", "onset": 2.0}, {"label": "C:maj", "raw": "C:maj", "t": "G:maj", "onset": 3.0}], "next_chord": "C:maj", "next_chord_t": "G:maj"}, {"bar": 42, "beats_per_bar": 4, "notes": [[67, 0.0, 1.5, 107], [69, 1.5, 0.5, 108], [67, 2.0, 1.5, 113], [69, 3.5, 0.25, 107], [67, 3.75, 0.25, 100]], "chords": [{"label": "C:maj", "raw": "C:maj", "t": "G:maj", "onset": 0.0}, {"label": "G:min", "raw": "G:min", "t": "D:min", "onset": 0.0}, {"label": "C:sus2", "raw": "C:sus2", "t": "G:sus2", "onset": 2.0}], "next_chord": "D:min", "next_chord_t": "A:min"}, {"bar": 43, "beats_per_bar": 4, "notes": [[65, 0.0, 1.0, 107], [65, 1.0, 0.5, 113], [67, 1.5, 0.25, 113], [69, 1.75, 1.75, 108], [74, 3.5, 0.25, 110], [77, 3.75, 0.25, 113]], "chords": [{"label": "D:min", "raw": "D:min", "t": "A:min", "onset": 0.0}], "next_chord": "A:min", "next_chord_t": "E:min"}, {"bar": 44, "beats_per_bar": 4, "notes": [[76, 0.0, 1.0, 119], [76, 1.0, 0.5, 114], [74, 1.5, 0.25, 108], [72, 1.75, 1.75, 102], [72, 3.5, 0.25, 102], [69, 3.75, 0.25, 102]], "chords": [{"label": "A:min", "raw": "A:min", "t": "E:min", "onset": 0.0}], "next_chord": "G:min", "next_chord_t": "D:min"}, {"bar": 45, "beats_per_bar": 4, "notes": [[67, 0.0, 1.5, 108], [67, 1.5, 0.25, 107], [69, 1.75, 0.25, 108], [67, 2.0, 0.5, 114], [65, 2.5, 0.5, 113], [62, 3.0, 0.25, 107], [65, 3.25, 0.75, 113]], "chords": [{"label": "G:min", "raw": "G:min", "t": "D:min", "onset": 0.0}, {"label": "C:maj", "raw": "C:maj", "t": "G:maj", "onset": 2.0}], "next_chord": "F:maj", "next_chord_t": "C:maj"}, {"bar": 46, "beats_per_bar": 4, "notes": [[65, 0.0, 3.0, 114], [65, 3.0, 0.25, 116], [67, 3.25, 0.5, 116], [69, 3.75, 0.25, 116]], "chords": [{"label": "F:maj", "raw": "F:maj", "t": "C:maj", "onset": 0.0}], "next_chord": "F:maj", "next_chord_t": "C:maj"}, {"bar": 47, "beats_per_bar": 4, "notes": [[72, 0.0, 1.75, 114], [72, 1.75, 0.25, 114], [74, 2.0, 0.5, 117], [72, 2.5, 0.5, 116], [69, 3.0, 0.5, 113], [67, 3.5, 0.5, 116]], "chords": [{"label": "F:maj", "raw": "F:maj", "t": "C:maj", "onset": 0.0}, {"label": "F:maj", "raw": "F:maj", "t": "C:maj", "onset": 0.0}], "next_chord": "D:min", "next_chord_t": "A:min"}, {"bar": 48, "beats_per_bar": 4, "notes": [[69, 0.0, 0.5, 114], [69, 0.5, 0.5, 110], [69, 1.0, 0.25, 113], [67, 1.25, 0.5, 110], [65, 1.75, 1.25, 107], [65, 3.0, 0.25, 116], [67, 3.25, 0.5, 114], [69, 3.75, 0.25, 114]], "chords": [{"label": "D:min", "raw": "D:min", "t": "A:min", "onset": 0.0}], "next_chord": "Bb:maj", "next_chord_t": "F:maj"}, {"bar": 49, "beats_per_bar": 4, "notes": [[77, 0.0, 1.75, 117], [77, 1.75, 0.25, 114], [79, 2.0, 0.5, 116], [77, 2.5, 0.5, 110], [74, 3.0, 0.25, 113], [72, 3.25, 0.5, 107], [69, 3.75, 0.25, 113]], "chords": [{"label": "Bb:maj", "raw": "Bb:maj", "t": "F:maj", "onset": 0.0}, {"label": "C:maj", "raw": "C:maj", "t": "G:maj", "onset": 2.0}], "next_chord": "F:maj", "next_chord_t": "C:maj"}, {"bar": 50, "beats_per_bar": 4, "notes": [[72, 0.0, 3.0, 117], [72, 3.0, 0.5, 117], [74, 3.5, 0.5, 119]], "chords": [{"label": "F:maj", "raw": "F:maj", "t": "C:maj", "onset": 0.0}], "next_chord": "F:maj", "next_chord_t": "C:maj"}, {"bar": 51, "beats_per_bar": 4, "notes": [[77, 0.0, 1.5, 123], [79, 1.5, 0.5, 117], [79, 2.0, 0.5, 114], [77, 2.5, 0.5, 119], [74, 3.0, 0.5, 117], [72, 3.5, 0.25, 116], [74, 3.75, 0.75, 117]], "chords": [{"label": "F:maj", "raw": "F:maj", "t": "C:maj", "onset": 0.0}], "next_chord": "F:maj", "next_chord_t": "C:maj"}, {"bar": 52, "beats_per_bar": 4, "notes": [[74, 0.5, 0.5, 114], [74, 1.0, 0.25, 113], [72, 1.25, 0.5, 114], [69, 1.75, 1.25, 113], [72, 3.0, 0.5, 114], [69, 3.5, 0.5, 119]], "chords": [{"label": "F:maj", "raw": "F:maj", "t": "C:maj", "onset": 0.0}, {"label": "D:min", "raw": "D:min", "t": "A:min", "onset": 0.0}], "next_chord": "G:min", "next_chord_t": "D:min"}, {"bar": 53, "beats_per_bar": 4, "notes": [[67, 0.0, 1.5, 119], [67, 1.5, 0.25, 117], [69, 1.75, 0.25, 114], [67, 2.0, 1.5, 119], [65, 3.5, 0.5, 116]], "chords": [{"label": "G:min", "raw": "G:min", "t": "D:min", "onset": 0.0}, {"label": "C:maj", "raw": "C:maj", "t": "G:maj", "onset": 2.0}], "next_chord": "C:maj", "next_chord_t": "G:maj"}, {"bar": 54, "beats_per_bar": 4, "notes": [[67, 0.0, 3.0, 119], [65, 3.0, 0.25, 116], [67, 3.25, 0.5, 116], [69, 3.75, 0.25, 116]], "chords": [{"label": "C:maj", "raw": "C:maj", "t": "G:maj", "onset": 0.0}], "next_chord": "F:maj", "next_chord_t": "C:maj"}, {"bar": 55, "beats_per_bar": 4, "notes": [[72, 0.0, 1.75, 114], [72, 1.75, 0.25, 114], [74, 2.0, 0.5, 117], [72, 2.5, 0.5, 116], [69, 3.0, 0.5, 113], [67, 3.5, 0.5, 116]], "chords": [{"label": "F:maj", "raw": "F:maj", "t": "C:maj", "onset": 0.0}], "next_chord": "D:min", "next_chord_t": "A:min"}, {"bar": 56, "beats_per_bar": 4, "notes": [[69, 0.0, 0.5, 114], [69, 0.5, 0.5, 110], [69, 1.0, 0.25, 113], [67, 1.25, 0.5, 110], [65, 1.75, 1.25, 107], [65, 3.0, 0.25, 116], [67, 3.25, 0.5, 114], [69, 3.75, 0.25, 114]], "chords": [{"label": "D:min", "raw": "D:min", "t": "A:min", "onset": 0.0}], "next_chord": "D:min", "next_chord_t": "A:min"}, {"bar": 57, "beats_per_bar": 4, "notes": [[77, 0.0, 1.75, 117], [77, 1.75, 0.25, 114], [79, 2.0, 0.5, 116], [77, 2.5, 0.5, 110], [74, 3.0, 0.25, 113], [72, 3.25, 0.5, 107], [69, 3.75, 0.25, 113]], "chords": [{"label": "D:min", "raw": "D:min", "t": "A:min", "onset": 0.0}, {"label": "Bb:maj", "raw": "Bb:maj", "t": "F:maj", "onset": 0.0}, {"label": "C:maj", "raw": "C:maj", "t": "G:maj", "onset": 2.0}], "next_chord": "F:maj", "next_chord_t": "C:maj"}, {"bar": 58, "beats_per_bar": 4, "notes": [[72, 0.0, 3.0, 117], [72, 3.0, 0.5, 117], [74, 3.5, 0.5, 119]], "chords": [{"label": "F:maj", "raw": "F:maj", "t": "C:maj", "onset": 0.0}], "next_chord": "F:maj", "next_chord_t": "C:maj"}, {"bar": 59, "beats_per_bar": 4, "notes": [[77, 0.0, 1.5, 123], [79, 1.5, 0.5, 117], [79, 2.0, 0.5, 114], [77, 2.5, 0.5, 119], [74, 3.0, 0.5, 117], [72, 3.5, 0.25, 116], [74, 3.75, 0.75, 117]], "chords": [{"label": "F:maj", "raw": "F:maj", "t": "C:maj", "onset": 0.0}], "next_chord": "D:min", "next_chord_t": "A:min"}, {"bar": 60, "beats_per_bar": 4, "notes": [[74, 0.5, 0.5, 114], [74, 1.0, 0.25, 113], [72, 1.25, 0.5, 114], [69, 1.75, 1.25, 113], [72, 3.0, 0.5, 114], [69, 3.5, 0.5, 119]], "chords": [{"label": "D:min", "raw": "D:min", "t": "A:min", "onset": 0.0}], "next_chord": "G:min", "next_chord_t": "D:min"}, {"bar": 61, "beats_per_bar": 4, "notes": [[67, 0.0, 1.5, 119], [67, 1.5, 0.25, 117], [69, 1.75, 0.25, 114], [67, 2.0, 0.25, 119], [65, 2.5, 0.25, 114], [62, 3.0, 0.5, 114], [65, 3.5, 1.0, 114]], "chords": [{"label": "G:min", "raw": "G:min", "t": "D:min", "onset": 0.0}, {"label": "C:maj", "raw": "C:maj", "t": "G:maj", "onset": 2.0}], "next_chord": "C:maj", "next_chord_t": "G:maj"}, {"bar": 62, "beats_per_bar": 4, "notes": [[65, 0.5, 2.5, 102], [72, 3.0, 0.5, 117], [74, 3.5, 0.5, 119]], "chords": [{"label": "C:maj", "raw": "C:maj", "t": "G:maj", "onset": 0.0}, {"label": "F:maj", "raw": "F:maj", "t": "C:maj", "onset": 0.0}], "next_chord": "Bb:maj7", "next_chord_t": "F:maj7"}, {"bar": 63, "beats_per_bar": 4, "notes": [[77, 0.0, 1.5, 123], [79, 1.5, 0.5, 117], [79, 2.0, 0.5, 114], [77, 2.5, 0.5, 119], [74, 3.0, 0.5, 117], [72, 3.5, 0.25, 116], [74, 3.75, 0.75, 117]], "chords": [{"label": "Bb:maj7", "raw": "Bb:maj7", "t": "F:maj7", "onset": 0.0}], "next_chord": "A:min", "next_chord_t": "E:min"}, {"bar": 64, "beats_per_bar": 4, "notes": [[74, 0.5, 0.5, 114], [74, 1.0, 0.25, 113], [72, 1.25, 0.5, 114], [69, 1.75, 1.25, 113], [72, 3.0, 0.5, 114], [69, 3.5, 0.5, 119]], "chords": [{"label": "A:min", "raw": "A:min", "t": "E:min", "onset": 0.0}, {"label": "D:maj", "raw": "D:maj", "t": "A:maj", "onset": 2.0}], "next_chord": "G:min", "next_chord_t": "D:min"}, {"bar": 65, "beats_per_bar": 4, "notes": [[67, 0.0, 1.5, 119], [67, 1.5, 0.25, 117], [69, 1.75, 0.25, 114], [67, 2.0, 0.5, 119], [65, 2.5, 0.75, 96], [62, 3.25, 0.5, 98], [65, 3.75, 1.0, 100]], "chords": [{"label": "G:min", "raw": "G:min", "t": "D:min", "onset": 0.0}, {"label": "C:maj", "raw": "C:maj", "t": "G:maj", "onset": 2.0}], "next_chord": "F:sus2", "next_chord_t": "C:sus2"}, {"bar": 66, "beats_per_bar": 4, "notes": [[65, 0.75, 1.5, 107]], "chords": [{"label": "F:sus2", "raw": "F:sus2", "t": "C:sus2", "onset": 0.0}, {"label": "F:maj", "raw": "F:maj", "t": "C:maj", "onset": 2.0}], "next_chord": "F:maj", "next_chord_t": "C:maj"}, {"bar": 67, "beats_per_bar": 4, "notes": [], "chords": [{"label": "F:maj", "raw": "F:maj", "t": "C:maj", "onset": 0.0}, {"label": "F:sus2", "raw": "F:sus2", "t": "C:sus2", "onset": 0.0}], "next_chord": "D:sus4", "next_chord_t": "A:sus4"}, {"bar": 68, "beats_per_bar": 4, "notes": [], "chords": [{"label": "D:sus4", "raw": "D:sus4", "t": "A:sus4", "onset": 0.0}, {"label": "D:min", "raw": "D:min", "t": "A:min", "onset": 2.0}], "next_chord": "Bb:maj7", "next_chord_t": "F:maj7"}, {"bar": 69, "beats_per_bar": 4, "notes": [], "chords": [{"label": "Bb:maj7", "raw": "Bb:maj7", "t": "F:maj7", "onset": 0.0}], "next_chord": "Bb:maj", "next_chord_t": "F:maj"}, {"bar": 70, "beats_per_bar": 4, "notes": [], "chords": [{"label": "Bb:maj", "raw": "Bb:maj", "t": "F:maj", "onset": 0.0}, {"label": "Bb:maj7", "raw": "Bb:maj7/7", "t": "F:maj7", "onset": 3.0}], "next_chord": "A:min", "next_chord_t": "E:min"}, {"bar": 71, "beats_per_bar": 4, "notes": [], "chords": [{"label": "A:min", "raw": "A:min", "t": "E:min", "onset": 0.0}, {"label": "A:7", "raw": "A:7/b7", "t": "E:7", "onset": 2.0}], "next_chord": "G:min", "next_chord_t": "D:min"}, {"bar": 72, "beats_per_bar": 4, "notes": [], "chords": [{"label": "G:min", "raw": "G:min", "t": "D:min", "onset": 0.0}, {"label": "C:maj", "raw": "C:maj", "t": "G:maj", "onset": 2.0}], "next_chord": "F:maj7", "next_chord_t": "C:maj7"}, {"bar": 73, "beats_per_bar": 4, "notes": [], "chords": [{"label": "F:maj7", "raw": "F:maj7", "t": "C:maj7", "onset": 0.0}, {"label": "F:sus2", "raw": "F:sus2", "t": "C:sus2", "onset": 2.0}], "next_chord": "F:maj", "next_chord_t": "C:maj"}, {"bar": 74, "beats_per_bar": 4, "notes": [], "chords": [{"label": "F:maj", "raw": "F:maj", "t": "C:maj", "onset": 0.0}], "next_chord": null, "next_chord_t": null}], "chord_sequence": [{"chord": "F:sus2", "raw": "F:sus2", "t": "C:sus2", "bar": 0, "beat": 0.0, "dur": 2.0}, {"chord": "F:maj", "raw": "F:maj", "t": "C:maj", "bar": 0, "beat": 2.0, "dur": 6.0}, {"chord": "D:maj", "raw": "D:maj", "t": "A:maj", "bar": 2, "beat": 0.0, "dur": 4.0}, {"chord": "G:min", "raw": "G:min", "t": "D:min", "bar": 3, "beat": 0.0, "dur": 4.0}, {"chord": "C:sus4", "raw": "C:sus4", "t": "G:sus4", "bar": 4, "beat": 0.0, "dur": 4.0}, {"chord": "C:maj", "raw": "C:maj", "t": "G:maj", "bar": 5, "beat": 0.0, "dur": 4.0}, {"chord": "F:sus2", "raw": "F:sus2", "t": "C:sus2", "bar": 6, "beat": 0.0, "dur": 3.0}, {"chord": "G:sus2", "raw": "G:sus2", "t": "D:sus2", "bar": 6, "beat": 3.0, "dur": 1.0}, {"chord": "A:min", "raw": "A:min", "t": "E:min", "bar": 7, "beat": 0.0, "dur": 4.0}, {"chord": "D:min", "raw": "D:min", "t": "A:min", "bar": 8, "beat": 0.0, "dur": 4.0}, {"chord": "G:sus4", "raw": "G:sus4", "t": "D:sus4", "bar": 9, "beat": 0.0, "dur": 4.0}, {"chord": "D:min", "raw": "D:min", "t": "A:min", "bar": 10, "beat": 0.0, "dur": 4.0}, {"chord": "A:min", "raw": "A:min", "t": "E:min", "bar": 11, "beat": 0.0, "dur": 4.0}, {"chord": "G:min", "raw": "G:min", "t": "D:min", "bar": 12, "beat": 0.0, "dur": 4.0}, {"chord": "C:sus4", "raw": "C:sus4", "t": "G:sus4", "bar": 13, "beat": 0.0, "dur": 2.0}, {"chord": "C:maj", "raw": "C:maj", "t": "G:maj", "bar": 13, "beat": 2.0, "dur": 2.0}, {"chord": "F:maj", "raw": "F:maj", "t": "C:maj", "bar": 14, "beat": 0.0, "dur": 1.0}, {"chord": "F:sus2", "raw": "F:sus2", "t": "C:sus2", "bar": 14, "beat": 1.0, "dur": 2.0}, {"chord": "F:maj", "raw": "F:maj", "t": "C:maj", "bar": 14, "beat": 3.0, "dur": 1.0}, {"chord": "A:min", "raw": "A:min", "t": "E:min", "bar": 15, "beat": 0.0, "dur": 4.0}, {"chord": "D:min", "raw": "D:min", "t": "A:min", "bar": 16, "beat": 0.0, "dur": 2.0}, {"chord": "D:min7", "raw": "D:min7/b7", "t": "A:min7", "bar": 16, "beat": 2.0, "dur": 1.0}, {"chord": "C:maj", "raw": "C:maj", "t": "G:maj", "bar": 16, "beat": 3.0, "dur": 1.0}, {"chord": "G:min", "raw": "G:min", "t": "D:min", "bar": 17, "beat": 0.0, "dur": 2.0}, {"chord": "C:sus2", "raw": "C:sus2", "t": "G:sus2", "bar": 17, "beat": 2.0, "dur": 2.0}, {"chord": "D:min", "raw": "D:min", "t": "A:min", "bar": 18, "beat": 0.0, "dur": 4.0}, {"chord": "A:min", "raw": "A:min", "t": "E:min", "bar": 19, "beat": 0.0, "dur": 4.0}, {"chord": "G:min", "raw": "G:min", "t": "D:min", "bar": 20, "beat": 0.0, "dur": 2.0}, {"chord": "C:maj", "raw": "C:maj", "t": "G:maj", "bar": 20, "beat": 2.0, "dur": 2.0}, {"chord": "F:maj", "raw": "F:maj", "t": "C:maj", "bar": 21, "beat": 0.0, "dur": 8.0}, {"chord": "D:min", "raw": "D:min", "t": "A:min", "bar": 23, "beat": 0.0, "dur": 4.0}, {"chord": "Bb:maj", "raw": "Bb:maj", "t": "F:maj", "bar": 24, "beat": 0.0, "dur": 2.0}, {"chord": "C:maj", "raw": "C:maj", "t": "G:maj", "bar": 24, "beat": 2.0, "dur": 2.0}, {"chord": "F:maj", "raw": "F:maj", "t": "C:maj", "bar": 25, "beat": 0.0, "dur": 8.0}, {"chord": "D:min", "raw": "D:min", "t": "A:min", "bar": 27, "beat": 0.0, "dur": 4.0}, {"chord": "G:min", "raw": "G:min", "t": "D:min", "bar": 28, "beat": 0.0, "dur": 2.0}, {"chord": "C:maj", "raw": "C:maj", "t": "G:maj", "bar": 28, "beat": 2.0, "dur": 2.0}, {"chord": "F:maj", "raw": "F:maj", "t": "C:maj", "bar": 29, "beat": 0.0, "dur": 4.0}, {"chord": "F:sus2", "raw": "F:sus2", "t": "C:sus2", "bar": 30, "beat": 0.0, "dur": 2.0}, {"chord": "F:maj", "raw": "F:maj", "t": "C:maj", "bar": 30, "beat": 2.0, "dur": 6.0}, {"chord": "D:maj", "raw": "D:maj", "t": "A:maj", "bar": 32, "beat": 0.0, "dur": 4.0}, {"chord": "D:min", "raw": "D:min", "t": "A:min", "bar": 33, "beat": 0.0, "dur": 4.0}, {"chord": "Bb:maj", "raw": "Bb:maj", "t": "F:maj", "bar": 34, "beat": 0.0, "dur": 4.0}, {"chord": "A:min", "raw": "A:min", "t": "E:min", "bar": 35, "beat": 0.0, "dur": 2.0}, {"chord": "D:min", "raw": "D:min", "t": "A:min", "bar": 35, "beat": 2.0, "dur": 2.0}, {"chord": "G:min", "raw": "G:min", "t": "D:min", "bar": 36, "beat": 0.0, "dur": 4.0}, {"chord": "C:maj", "raw": "C:maj", "t": "G:maj", "bar": 37, "beat": 0.0, "dur": 8.0}, {"chord": "F:maj", "raw": "F:maj", "t": "C:maj", "bar": 39, "beat": 0.0, "dur": 1.0}, {"chord": "F:sus2", "raw": "F:sus2", "t": "C:sus2", "bar": 39, "beat": 1.0, "dur": 2.0}, {"chord": "F:maj", "raw": "F:maj", "t": "C:maj", "bar": 39, "beat": 3.0, "dur": 1.0}, {"chord": "A:min", "raw": "A:min", "t": "E:min", "bar": 40, "beat": 0.0, "dur": 4.0}, {"chord": "D:min", "raw": "D:min", "t": "A:min", "bar": 41, "beat": 0.0, "dur": 2.0}, {"chord": "D:min7", "raw": "D:min7/b7", "t": "A:min7", "bar": 41, "beat": 2.0, "dur": 1.0}, {"chord": "C:maj", "raw": "C:maj", "t": "G:maj", "bar": 41, "beat": 3.0, "dur": 1.0}, {"chord": "G:min", "raw": "G:min", "t": "D:min", "bar": 42, "beat": 0.0, "dur": 2.0}, {"chord": "C:sus2", "raw": "C:sus2", "t": "G:sus2", "bar": 42, "beat": 2.0, "dur": 2.0}, {"chord": "D:min", "raw": "D:min", "t": "A:min", "bar": 43, "beat": 0.0, "dur": 4.0}, {"chord": "A:min", "raw": "A:min", "t": "E:min", "bar": 44, "beat": 0.0, "dur": 4.0}, {"chord": "G:min", "raw": "G:min", "t": "D:min", "bar": 45, "beat": 0.0, "dur": 2.0}, {"chord": "C:maj", "raw": "C:maj", "t": "G:maj", "bar": 45, "beat": 2.0, "dur": 2.0}, {"chord": "F:maj", "raw": "F:maj", "t": "C:maj", "bar": 46, "beat": 0.0, "dur": 8.0}, {"chord": "D:min", "raw": "D:min", "t": "A:min", "bar": 48, "beat": 0.0, "dur": 4.0}, {"chord": "Bb:maj", "raw": "Bb:maj", "t": "F:maj", "bar": 49, "beat": 0.0, "dur": 2.0}, {"chord": "C:maj", "raw": "C:maj", "t": "G:maj", "bar": 49, "beat": 2.0, "dur": 2.0}, {"chord": "F:maj", "raw": "F:maj", "t": "C:maj", "bar": 50, "beat": 0.0, "dur": 8.0}, {"chord": "D:min", "raw": "D:min", "t": "A:min", "bar": 52, "beat": 0.0, "dur": 4.0}, {"chord": "G:min", "raw": "G:min", "t": "D:min", "bar": 53, "beat": 0.0, "dur": 2.0}, {"chord": "C:maj", "raw": "C:maj", "t": "G:maj", "bar": 53, "beat": 2.0, "dur": 6.0}, {"chord": "F:maj", "raw": "F:maj", "t": "C:maj", "bar": 55, "beat": 0.0, "dur": 4.0}, {"chord": "D:min", "raw": "D:min", "t": "A:min", "bar": 56, "beat": 0.0, "dur": 4.0}, {"chord": "Bb:maj", "raw": "Bb:maj", "t": "F:maj", "bar": 57, "beat": 0.0, "dur": 2.0}, {"chord": "C:maj", "raw": "C:maj", "t": "G:maj", "bar": 57, "beat": 2.0, "dur": 2.0}, {"chord": "F:maj", "raw": "F:maj", "t": "C:maj", "bar": 58, "beat": 0.0, "dur": 8.0}, {"chord": "D:min", "raw": "D:min", "t": "A:min", "bar": 60, "beat": 0.0, "dur": 4.0}, {"chord": "G:min", "raw": "G:min", "t": "D:min", "bar": 61, "beat": 0.0, "dur": 2.0}, {"chord": "C:maj", "raw": "C:maj", "t": "G:maj", "bar": 61, "beat": 2.0, "dur": 2.0}, {"chord": "F:maj", "raw": "F:maj", "t": "C:maj", "bar": 62, "beat": 0.0, "dur": 4.0}, {"chord": "Bb:maj7", "raw": "Bb:maj7", "t": "F:maj7", "bar": 63, "beat": 0.0, "dur": 4.0}, {"chord": "A:min", "raw": "A:min", "t": "E:min", "bar": 64, "beat": 0.0, "dur": 2.0}, {"chord": "D:maj", "raw": "D:maj", "t": "A:maj", "bar": 64, "beat": 2.0, "dur": 2.0}, {"chord": "G:min", "raw": "G:min", "t": "D:min", "bar": 65, "beat": 0.0, "dur": 2.0}, {"chord": "C:maj", "raw": "C:maj", "t": "G:maj", "bar": 65, "beat": 2.0, "dur": 2.0}, {"chord": "F:sus2", "raw": "F:sus2", "t": "C:sus2", "bar": 66, "beat": 0.0, "dur": 2.0}, {"chord": "F:maj", "raw": "F:maj", "t": "C:maj", "bar": 66, "beat": 2.0, "dur": 2.0}, {"chord": "F:sus2", "raw": "F:sus2", "t": "C:sus2", "bar": 67, "beat": 0.0, "dur": 4.0}, {"chord": "D:sus4", "raw": "D:sus4", "t": "A:sus4", "bar": 68, "beat": 0.0, "dur": 2.0}, {"chord": "D:min", "raw": "D:min", "t": "A:min", "bar": 68, "beat": 2.0, "dur": 3.0}, {"chord": "Bb:maj7", "raw": "Bb:maj7", "t": "F:maj7", "bar": 69, "beat": 0.0, "dur": 4.0}, {"chord": "Bb:maj", "raw": "Bb:maj", "t": "F:maj", "bar": 70, "beat": 0.0, "dur": 3.0}, {"chord": "Bb:maj7", "raw": "Bb:maj7/7", "t": "F:maj7", "bar": 70, "beat": 3.0, "dur": 1.0}, {"chord": "A:min", "raw": "A:min", "t": "E:min", "bar": 71, "beat": 0.0, "dur": 2.0}, {"chord": "A:7", "raw": "A:7/b7", "t": "E:7", "bar": 71, "beat": 2.0, "dur": 2.0}, {"chord": "G:min", "raw": "G:min", "t": "D:min", "bar": 72, "beat": 0.0, "dur": 2.0}, {"chord": "C:maj", "raw": "C:maj", "t": "G:maj", "bar": 72, "beat": 2.0, "dur": 2.0}, {"chord": "F:maj7", "raw": "F:maj7", "t": "C:maj7", "bar": 73, "beat": 0.0, "dur": 2.0}, {"chord": "F:sus2", "raw": "F:sus2", "t": "C:sus2", "bar": 73, "beat": 2.0, "dur": 2.0}, {"chord": "F:maj", "raw": "F:maj", "t": "C:maj", "bar": 74, "beat": 0.0, "dur": 5.0}]}